{"config": {"view": {"continuousWidth": 300, "continuousHeight": 300}}, "vconcat": [{"mark": {"type": "boxplot"}, "encoding": {"color": {"field": "crossing", "legend": {"title": "crossing"}, "type": "nominal"}, "tooltip": {"field": "age", "type": "quantitative"}, "x": {"field": "age", "scale": {"zero": false}, "type": "quantitative"}, "y": {"field": "crossing", "type": "nominal"}}, "height": 200, "title": "Crossings Update Age (Years)", "transform": [{"filter": {"param": "brush"}}], "width": 400}, {"mark": {"type": "bar"}, "encoding": {"color": {"field": "crossing", "legend": {"title": "crossing"}, "type": "nominal"}, "tooltip": {"aggregate": "count", "title": "count", "type": "quantitative"}, "x": {"bin": {"maxbins": 10}, "field": "age", "type": "quantitative"}, "y": {"aggregate": "count", "type": "quantitative"}}, "name": "view_7"}], "data": {"name": "data-f42a48edbaba5b9bc767bf27f5af8c14"}, "params": [{"name": "brush", "select": {"type": "interval", "encodings": ["x"]}, "bind": "scales", "views": ["view_7"]}], "resolve": {"scale": {"x": "shared"}}, "$schema": "https://vega.github.io/schema/vega-lite/v5.20.1.json", "datasets": {"data-f42a48edbaba5b9bc767bf27f5af8c14": [{"age": 1.0212183436002737, "crossing": "unmarked"}, {"age": 1.3388090349075976, "crossing": "unmarked"}, {"age": 2.0944558521560577, "crossing": "?"}, {"age": null, "crossing": "?"}, {"age": null, "crossing": "?"}, {"age": null, "crossing": "?"}, {"age": 2.8884325804243667, "crossing": "?"}, {"age": 2.652977412731006, "crossing": "marked"}, {"age": 0.7529089664613279, "crossing": "traffic_signals"}, {"age": 0.7529089664613279, "crossing": "?"}, {"age": 2.023271731690623, "crossing": "?"}, {"age": 0.5776865160848734, "crossing": "?"}, {"age": 1.273100616016427, "crossing": "unmarked"}, {"age": 1.5605749486652978, "crossing": "marked"}, {"age": 1.5605749486652978, "crossing": "marked"}, {"age": 2.8884325804243667, "crossing": "zebra"}, {"age": 2.8884325804243667, "crossing": "zebra"}, {"age": 0.02737850787132101, "crossing": "zebra"}, {"age": 0.13415468856947296, "crossing": "uncontrolled"}, {"age": 1.3360711841204653, "crossing": "traffic_signals"}, {"age": 1.3360711841204653, "crossing": "traffic_signals"}, {"age": 0.9555099247091033, "crossing": "uncontrolled"}, {"age": 1.3360711841204653, "crossing": "traffic_signals"}, {"age": 1.2101300479123889, "crossing": "zebra"}, {"age": 3.7125256673511293, "crossing": "zebra"}, {"age": 3.7125256673511293, "crossing": "zebra"}, {"age": 3.7234770704996576, "crossing": "zebra"}, {"age": 6.034223134839151, "crossing": "zebra"}, {"age": 6.034223134839151, "crossing": "zebra"}, {"age": 3.707049965776865, "crossing": "zebra"}, {"age": 3.707049965776865, "crossing": "zebra"}, {"age": 1.3388090349075976, "crossing": "traffic_signals"}, {"age": 1.3388090349075976, "crossing": "traffic_signals"}, {"age": 1.3388090349075976, "crossing": "traffic_signals"}, {"age": 1.3388090349075976, "crossing": "traffic_signals"}, {"age": 2.8528405201916494, "crossing": "marked"}, {"age": 5.932922655715264, "crossing": "marked"}, {"age": 5.932922655715264, "crossing": "marked"}, {"age": 1.7084188911704312, "crossing": "marked"}, {"age": 2.135523613963039, "crossing": "?"}, {"age": 5.607118412046543, "crossing": "marked"}, {"age": 0.974674880219028, "crossing": "traffic_signals"}, {"age": 1.3360711841204653, "crossing": "traffic_signals"}, {"age": 1.3360711841204653, "crossing": "traffic_signals"}, {"age": 2.9869952087611225, "crossing": "marked"}, {"age": 1.7084188911704312, "crossing": "unmarked"}, {"age": 1.3169062286105406, "crossing": "uncontrolled"}, {"age": 1.3169062286105406, "crossing": "uncontrolled"}, {"age": 0.12046543463381246, "crossing": "uncontrolled"}, {"age": 0.13141683778234087, "crossing": "uncontrolled"}, {"age": 1.3388090349075976, "crossing": "traffic_signals"}, {"age": 0.5913757700205339, "crossing": "traffic_signals"}, {"age": 1.3388090349075976, "crossing": "traffic_signals"}, {"age": 5.722108145106092, "crossing": "marked"}, {"age": 1.3169062286105406, "crossing": "uncontrolled"}, {"age": 4.878850102669404, "crossing": "zebra"}, {"age": 2.3846680355920604, "crossing": "?"}, {"age": 1.0787132101300478, "crossing": "unmarked"}, {"age": 1.1800136892539357, "crossing": "unmarked"}, {"age": 1.3059548254620124, "crossing": "unmarked"}, {"age": 4.854209445585216, "crossing": "?"}, {"age": 1.0595482546201231, "crossing": "uncontrolled"}, {"age": 4.922655715263518, "crossing": "?"}, {"age": 1.626283367556468, "crossing": "unmarked"}, {"age": 0.7529089664613279, "crossing": "unmarked"}, {"age": 3.19233401779603, "crossing": "unmarked"}, {"age": 3.19233401779603, "crossing": "unmarked"}, {"age": 3.19233401779603, "crossing": "unmarked"}, {"age": 3.479808350444901, "crossing": "unmarked"}, {"age": 3.19233401779603, "crossing": "unmarked"}, {"age": 3.19233401779603, "crossing": "unmarked"}, {"age": 3.479808350444901, "crossing": "unmarked"}, {"age": 3.479808350444901, "crossing": "unmarked"}, {"age": 1.7193702943189597, "crossing": "unmarked"}, {"age": 2.026009582477755, "crossing": "unmarked"}, {"age": 3.479808350444901, "crossing": "unmarked"}, {"age": 3.479808350444901, "crossing": "unmarked"}, {"age": 3.479808350444901, "crossing": "unmarked"}, {"age": 0.8733744010951403, "crossing": "unmarked"}, {"age": 3.19233401779603, "crossing": "unmarked"}, {"age": 3.19233401779603, "crossing": "unmarked"}, {"age": 2.132785763175907, "crossing": "unmarked"}, {"age": 2.132785763175907, "crossing": "unmarked"}, {"age": 2.132785763175907, "crossing": "unmarked"}, {"age": 2.0369609856262834, "crossing": "unmarked"}, {"age": 2.0369609856262834, "crossing": "unmarked"}, {"age": 2.132785763175907, "crossing": "unmarked"}, {"age": 2.132785763175907, "crossing": "unmarked"}, {"age": 2.132785763175907, "crossing": "unmarked"}, {"age": 2.132785763175907, "crossing": "unmarked"}, {"age": 3.479808350444901, "crossing": "unmarked"}, {"age": 0.7529089664613279, "crossing": "unmarked"}, {"age": 1.6180698151950719, "crossing": "marked"}, {"age": 1.6180698151950719, "crossing": "marked"}, {"age": 1.568788501026694, "crossing": "marked"}, {"age": 2.132785763175907, "crossing": "unmarked"}, {"age": 2.132785763175907, "crossing": "unmarked"}, {"age": 2.132785763175907, "crossing": "unmarked"}, {"age": 0.7529089664613279, "crossing": "unmarked"}, {"age": 3.4743326488706368, "crossing": "marked"}, {"age": 3.4743326488706368, "crossing": "marked"}, {"age": 0.7529089664613279, "crossing": "marked"}, {"age": 0.7529089664613279, "crossing": "marked"}, {"age": 0.7529089664613279, "crossing": "marked"}, {"age": 3.4743326488706368, "crossing": "marked"}, {"age": 0.7529089664613279, "crossing": "marked"}, {"age": 2.132785763175907, "crossing": "marked"}, {"age": 2.132785763175907, "crossing": "marked"}, {"age": 1.6180698151950719, "crossing": "unmarked"}, {"age": 3.4743326488706368, "crossing": "unmarked"}, {"age": 3.4743326488706368, "crossing": "unmarked"}, {"age": 3.4743326488706368, "crossing": "unmarked"}, {"age": 2.132785763175907, "crossing": "marked"}, {"age": 2.132785763175907, "crossing": "marked"}, {"age": 2.132785763175907, "crossing": "marked"}, {"age": 0.8624229979466119, "crossing": "marked"}, {"age": 2.132785763175907, "crossing": "marked"}, {"age": 2.132785763175907, "crossing": "unmarked"}, {"age": 2.132785763175907, "crossing": "marked"}, {"age": 2.132785763175907, "crossing": "marked"}, {"age": 2.132785763175907, "crossing": "marked"}, {"age": 3.4743326488706368, "crossing": "marked"}, {"age": 3.4743326488706368, "crossing": "marked"}, {"age": 3.19233401779603, "crossing": "marked"}, {"age": 0.8624229979466119, "crossing": "marked"}, {"age": 1.2292950034223136, "crossing": "marked"}, {"age": 1.2292950034223136, "crossing": "marked"}, {"age": 1.949349760438056, "crossing": "marked"}, {"age": 1.9301848049281314, "crossing": "marked"}, {"age": 1.949349760438056, "crossing": "marked"}, {"age": 2.132785763175907, "crossing": "marked"}, {"age": 2.132785763175907, "crossing": "marked"}, {"age": 2.132785763175907, "crossing": "marked"}, {"age": 2.132785763175907, "crossing": "marked"}, {"age": 3.4743326488706368, "crossing": "unmarked"}, {"age": 2.16290212183436, "crossing": "unmarked"}, {"age": 3.4743326488706368, "crossing": "unmarked"}, {"age": 3.4743326488706368, "crossing": "unmarked"}, {"age": 1.9794661190965093, "crossing": "unmarked"}, {"age": 2.5023956194387407, "crossing": "unmarked"}, {"age": 3.0965092402464065, "crossing": "marked"}, {"age": 3.4743326488706368, "crossing": "unmarked"}, {"age": 3.4743326488706368, "crossing": "unmarked"}, {"age": 3.1047227926078027, "crossing": "unmarked"}, {"age": 3.4743326488706368, "crossing": "unmarked"}, {"age": 3.4743326488706368, "crossing": "unmarked"}, {"age": 3.4743326488706368, "crossing": "unmarked"}, {"age": 3.1047227926078027, "crossing": "unmarked"}, {"age": 0.8624229979466119, "crossing": "unmarked"}, {"age": 0.8624229979466119, "crossing": "unmarked"}, {"age": 3.4743326488706368, "crossing": "unmarked"}, {"age": 3.4743326488706368, "crossing": "unmarked"}, {"age": 3.4743326488706368, "crossing": "unmarked"}, {"age": 3.4743326488706368, "crossing": "unmarked"}, {"age": 3.4743326488706368, "crossing": "unmarked"}, {"age": 3.4743326488706368, "crossing": "unmarked"}, {"age": 3.1047227926078027, "crossing": "unmarked"}, {"age": 3.4743326488706368, "crossing": "unmarked"}, {"age": 3.4743326488706368, "crossing": "unmarked"}, {"age": 3.4743326488706368, "crossing": "unmarked"}, {"age": 2.42299794661191, "crossing": "unmarked"}, {"age": 3.1047227926078027, "crossing": "unmarked"}, {"age": 3.1047227926078027, "crossing": "unmarked"}, {"age": 3.1047227926078027, "crossing": "unmarked"}, {"age": 3.4743326488706368, "crossing": "unmarked"}, {"age": 3.4743326488706368, "crossing": "unmarked"}, {"age": 3.455167693360712, "crossing": "unmarked"}, {"age": 3.4743326488706368, "crossing": "unmarked"}, {"age": 3.4743326488706368, "crossing": "unmarked"}, {"age": 3.4743326488706368, "crossing": "unmarked"}, {"age": 3.4743326488706368, "crossing": "unmarked"}, {"age": 3.4743326488706368, "crossing": "unmarked"}, {"age": 3.4743326488706368, "crossing": "unmarked"}, {"age": 3.4743326488706368, "crossing": "unmarked"}, {"age": 3.4743326488706368, "crossing": "unmarked"}, {"age": 3.4743326488706368, "crossing": "unmarked"}, {"age": 3.4743326488706368, "crossing": "unmarked"}, {"age": 3.4743326488706368, "crossing": "unmarked"}, {"age": 3.4743326488706368, "crossing": "unmarked"}, {"age": 3.4743326488706368, "crossing": "unmarked"}, {"age": 3.4743326488706368, "crossing": "unmarked"}, {"age": 3.4743326488706368, "crossing": "unmarked"}, {"age": 3.4743326488706368, "crossing": "unmarked"}, {"age": 2.132785763175907, "crossing": "marked"}, {"age": 2.132785763175907, "crossing": "marked"}, {"age": 2.132785763175907, "crossing": "marked"}, {"age": 2.132785763175907, "crossing": "marked"}, {"age": 0.8624229979466119, "crossing": "marked"}, {"age": 2.132785763175907, "crossing": "marked"}, {"age": 0.8624229979466119, "crossing": "marked"}, {"age": 2.132785763175907, "crossing": "marked"}, {"age": 3.4743326488706368, "crossing": "marked"}, {"age": 3.4743326488706368, "crossing": "unmarked"}, {"age": 3.4743326488706368, "crossing": "unmarked"}, {"age": 3.4743326488706368, "crossing": "unmarked"}, {"age": 3.4743326488706368, "crossing": "unmarked"}, {"age": 3.4743326488706368, "crossing": "unmarked"}, {"age": 3.4743326488706368, "crossing": "unmarked"}, {"age": 0.7529089664613279, "crossing": "marked"}, {"age": 2.132785763175907, "crossing": "unmarked"}, {"age": 2.132785763175907, "crossing": "unmarked"}, {"age": 2.132785763175907, "crossing": "unmarked"}, {"age": 2.132785763175907, "crossing": "unmarked"}, {"age": 2.132785763175907, "crossing": "unmarked"}, {"age": 2.132785763175907, "crossing": "unmarked"}, {"age": 2.132785763175907, "crossing": "unmarked"}, {"age": 2.132785763175907, "crossing": "unmarked"}, {"age": 2.132785763175907, "crossing": "unmarked"}, {"age": 2.132785763175907, "crossing": "unmarked"}, {"age": 2.132785763175907, "crossing": "unmarked"}, {"age": 2.132785763175907, "crossing": "unmarked"}, {"age": 2.132785763175907, "crossing": "unmarked"}, {"age": 2.132785763175907, "crossing": "unmarked"}, {"age": 2.132785763175907, "crossing": "unmarked"}, {"age": 2.132785763175907, "crossing": "unmarked"}, {"age": 3.4715947980835042, "crossing": "unmarked"}, {"age": 3.4715947980835042, "crossing": "unmarked"}, {"age": 3.4715947980835042, "crossing": "unmarked"}, {"age": 3.4715947980835042, "crossing": "unmarked"}, {"age": 3.4715947980835042, "crossing": "unmarked"}, {"age": 3.4715947980835042, "crossing": "unmarked"}, {"age": 3.4715947980835042, "crossing": "unmarked"}, {"age": 3.4715947980835042, "crossing": "unmarked"}, {"age": 0.8733744010951403, "crossing": "unmarked"}, {"age": 0.8733744010951403, "crossing": "unmarked"}, {"age": 3.4715947980835042, "crossing": "unmarked"}, {"age": 0.8733744010951403, "crossing": "unmarked"}, {"age": 0.8733744010951403, "crossing": "unmarked"}, {"age": 3.4715947980835042, "crossing": "unmarked"}, {"age": 3.4715947980835042, "crossing": "unmarked"}, {"age": 3.4715947980835042, "crossing": "unmarked"}, {"age": 3.4715947980835042, "crossing": "unmarked"}, {"age": 3.4715947980835042, "crossing": "unmarked"}, {"age": 3.4715947980835042, "crossing": "unmarked"}, {"age": 2.132785763175907, "crossing": "unmarked"}, {"age": 2.132785763175907, "crossing": "unmarked"}, {"age": 2.132785763175907, "crossing": "unmarked"}, {"age": 2.132785763175907, "crossing": "unmarked"}, {"age": 2.132785763175907, "crossing": "unmarked"}, {"age": 2.132785763175907, "crossing": "unmarked"}, {"age": 2.132785763175907, "crossing": "unmarked"}, {"age": 2.132785763175907, "crossing": "unmarked"}, {"age": 2.132785763175907, "crossing": "unmarked"}, {"age": 0.8624229979466119, "crossing": "unmarked"}, {"age": 0.47638603696098564, "crossing": "unmarked"}, {"age": 0.47638603696098564, "crossing": "unmarked"}, {"age": 0.8624229979466119, "crossing": "unmarked"}, {"age": 2.132785763175907, "crossing": "unmarked"}, {"age": 2.132785763175907, "crossing": "unmarked"}, {"age": 2.132785763175907, "crossing": "unmarked"}, {"age": 2.132785763175907, "crossing": "unmarked"}, {"age": 2.132785763175907, "crossing": "unmarked"}, {"age": 2.132785763175907, "crossing": "unmarked"}, {"age": 2.132785763175907, "crossing": "unmarked"}, {"age": 2.132785763175907, "crossing": "unmarked"}, {"age": 2.132785763175907, "crossing": "unmarked"}, {"age": 2.132785763175907, "crossing": "unmarked"}, {"age": 2.132785763175907, "crossing": "unmarked"}, {"age": 2.132785763175907, "crossing": "unmarked"}, {"age": 2.132785763175907, "crossing": "unmarked"}, {"age": 2.132785763175907, "crossing": "unmarked"}, {"age": 2.132785763175907, "crossing": "unmarked"}, {"age": 2.132785763175907, "crossing": "unmarked"}, {"age": 2.132785763175907, "crossing": "unmarked"}, {"age": 2.132785763175907, "crossing": "unmarked"}, {"age": 2.132785763175907, "crossing": "unmarked"}, {"age": 2.132785763175907, "crossing": "unmarked"}, {"age": 2.132785763175907, "crossing": "unmarked"}, {"age": 2.132785763175907, "crossing": "unmarked"}, {"age": 2.132785763175907, "crossing": "unmarked"}, {"age": 2.132785763175907, "crossing": "unmarked"}, {"age": 2.132785763175907, "crossing": "unmarked"}, {"age": 2.132785763175907, "crossing": "unmarked"}, {"age": 2.132785763175907, "crossing": "unmarked"}, {"age": 2.132785763175907, "crossing": "unmarked"}, {"age": 2.132785763175907, "crossing": "unmarked"}, {"age": 2.132785763175907, "crossing": "unmarked"}, {"age": 2.132785763175907, "crossing": "unmarked"}, {"age": 2.132785763175907, "crossing": "unmarked"}, {"age": 0.8624229979466119, "crossing": "unmarked"}, {"age": 2.132785763175907, "crossing": "unmarked"}, {"age": 2.132785763175907, "crossing": "unmarked"}, {"age": 2.132785763175907, "crossing": "unmarked"}, {"age": 2.132785763175907, "crossing": "unmarked"}, {"age": 2.132785763175907, "crossing": "unmarked"}, {"age": 2.132785763175907, "crossing": "unmarked"}, {"age": 2.132785763175907, "crossing": "unmarked"}, {"age": 2.132785763175907, "crossing": "unmarked"}, {"age": 2.132785763175907, "crossing": "unmarked"}, {"age": 1.949349760438056, "crossing": "unmarked"}, {"age": 2.132785763175907, "crossing": "unmarked"}, {"age": 3.460643394934976, "crossing": "unmarked"}, {"age": 3.460643394934976, "crossing": "unmarked"}, {"age": 3.460643394934976, "crossing": "unmarked"}, {"age": 3.460643394934976, "crossing": "unmarked"}, {"age": 3.460643394934976, "crossing": "unmarked"}, {"age": 3.460643394934976, "crossing": "unmarked"}, {"age": 3.460643394934976, "crossing": "unmarked"}, {"age": 3.460643394934976, "crossing": "unmarked"}, {"age": 3.460643394934976, "crossing": "unmarked"}, {"age": 2.4476386036960984, "crossing": "unmarked"}, {"age": 3.4113620807665983, "crossing": "unmarked"}, {"age": 3.460643394934976, "crossing": "unmarked"}, {"age": 3.460643394934976, "crossing": "unmarked"}, {"age": 3.457905544147844, "crossing": "unmarked"}, {"age": 0.8733744010951403, "crossing": "unmarked"}, {"age": 3.457905544147844, "crossing": "unmarked"}, {"age": 3.457905544147844, "crossing": "unmarked"}, {"age": 3.457905544147844, "crossing": "unmarked"}, {"age": 3.457905544147844, "crossing": "unmarked"}, {"age": 3.457905544147844, "crossing": "unmarked"}, {"age": 3.457905544147844, "crossing": "marked"}, {"age": 3.457905544147844, "crossing": "unmarked"}, {"age": 3.457905544147844, "crossing": "unmarked"}, {"age": 3.457905544147844, "crossing": "unmarked"}, {"age": 3.457905544147844, "crossing": "unmarked"}, {"age": 3.457905544147844, "crossing": "unmarked"}, {"age": 3.457905544147844, "crossing": "unmarked"}, {"age": 3.4469541409993156, "crossing": "unmarked"}, {"age": 3.457905544147844, "crossing": "unmarked"}, {"age": 3.457905544147844, "crossing": "unmarked"}, {"age": 0.8624229979466119, "crossing": "unmarked"}, {"age": 3.457905544147844, "crossing": "unmarked"}, {"age": 0.8624229979466119, "crossing": "unmarked"}, {"age": 3.457905544147844, "crossing": "unmarked"}, {"age": 2.132785763175907, "crossing": "unmarked"}, {"age": 2.132785763175907, "crossing": "unmarked"}, {"age": 1.919233401779603, "crossing": "unmarked"}, {"age": 2.132785763175907, "crossing": "unmarked"}, {"age": 2.132785763175907, "crossing": "unmarked"}, {"age": 2.132785763175907, "crossing": "unmarked"}, {"age": 1.9794661190965093, "crossing": "unmarked"}, {"age": 3.1047227926078027, "crossing": "unmarked"}, {"age": 3.1047227926078027, "crossing": "unmarked"}, {"age": 1.9794661190965093, "crossing": "unmarked"}, {"age": 3.2306639288158796, "crossing": "unmarked"}, {"age": 2.0369609856262834, "crossing": "unmarked"}, {"age": 0.7392197125256673, "crossing": "unmarked"}, {"age": 2.020533880903491, "crossing": "unmarked"}, {"age": 1.9794661190965093, "crossing": "unmarked"}, {"age": 1.9794661190965093, "crossing": "unmarked"}, {"age": 2.0369609856262834, "crossing": "unmarked"}, {"age": 1.995893223819302, "crossing": "unmarked"}, {"age": 1.995893223819302, "crossing": "unmarked"}, {"age": 1.995893223819302, "crossing": "unmarked"}, {"age": 1.995893223819302, "crossing": "unmarked"}, {"age": 1.995893223819302, "crossing": "unmarked"}, {"age": 1.995893223819302, "crossing": "unmarked"}, {"age": 1.995893223819302, "crossing": "unmarked"}, {"age": 1.995893223819302, "crossing": "unmarked"}, {"age": 0.8624229979466119, "crossing": "unmarked"}, {"age": 0.7529089664613279, "crossing": "unmarked"}, {"age": 1.6098562628336757, "crossing": "unmarked"}, {"age": 3.455167693360712, "crossing": "unmarked"}, {"age": 3.455167693360712, "crossing": "unmarked"}, {"age": 1.6098562628336757, "crossing": "unmarked"}, {"age": 0.8788501026694046, "crossing": "unmarked"}, {"age": 0.7529089664613279, "crossing": "unmarked"}, {"age": 2.099931553730322, "crossing": "unmarked"}, {"age": 2.4668035592060233, "crossing": "unmarked"}, {"age": 2.4668035592060233, "crossing": "unmarked"}, {"age": 3.436002737850787, "crossing": "unmarked"}, {"age": 3.4524298425735798, "crossing": "unmarked"}, {"age": 3.4524298425735798, "crossing": "unmarked"}, {"age": 3.1047227926078027, "crossing": "unmarked"}, {"age": 3.1047227926078027, "crossing": "unmarked"}, {"age": 3.1047227926078027, "crossing": "unmarked"}, {"age": 3.19233401779603, "crossing": "unmarked"}, {"age": 0.8624229979466119, "crossing": "unmarked"}, {"age": 3.4524298425735798, "crossing": "unmarked"}, {"age": 3.4524298425735798, "crossing": "unmarked"}, {"age": 0.7392197125256673, "crossing": "unmarked"}, {"age": 0.8624229979466119, "crossing": "unmarked"}, {"age": 2.132785763175907, "crossing": "unmarked"}, {"age": 1.514031485284052, "crossing": "marked"}, {"age": 2.132785763175907, "crossing": "marked"}, {"age": 2.132785763175907, "crossing": "unmarked"}, {"age": 1.5304585900068446, "crossing": "unmarked"}, {"age": 2.132785763175907, "crossing": "unmarked"}, {"age": 2.132785763175907, "crossing": "unmarked"}, {"age": 2.132785763175907, "crossing": "unmarked"}, {"age": 2.132785763175907, "crossing": "unmarked"}, {"age": 1.516769336071184, "crossing": "unmarked"}, {"age": 2.132785763175907, "crossing": "unmarked"}, {"age": 2.132785763175907, "crossing": "unmarked"}, {"age": 1.1827515400410678, "crossing": "unmarked"}, {"age": 2.132785763175907, "crossing": "unmarked"}, {"age": 2.132785763175907, "crossing": "unmarked"}, {"age": 1.514031485284052, "crossing": "unmarked"}, {"age": 2.132785763175907, "crossing": "unmarked"}, {"age": 1.5304585900068446, "crossing": "unmarked"}, {"age": 1.5304585900068446, "crossing": "unmarked"}, {"age": 3.0965092402464065, "crossing": "unmarked"}, {"age": 3.0965092402464065, "crossing": "unmarked"}, {"age": 2.187542778918549, "crossing": "unmarked"}, {"age": 0.7529089664613279, "crossing": "unmarked"}, {"age": 0.7529089664613279, "crossing": "unmarked"}, {"age": 0.7529089664613279, "crossing": "unmarked"}, {"age": 0.7529089664613279, "crossing": "unmarked"}, {"age": 3.436002737850787, "crossing": "unmarked"}, {"age": 2.4668035592060233, "crossing": "unmarked"}, {"age": 2.4668035592060233, "crossing": "unmarked"}, {"age": 2.4668035592060233, "crossing": "unmarked"}, {"age": 2.4668035592060233, "crossing": "unmarked"}, {"age": 0.8788501026694046, "crossing": "marked"}, {"age": 3.0855578370978782, "crossing": "unmarked"}, {"age": 3.436002737850787, "crossing": "unmarked"}, {"age": 0.8788501026694046, "crossing": "marked"}, {"age": 3.19233401779603, "crossing": "unmarked"}, {"age": 3.0965092402464065, "crossing": "marked"}, {"age": 1.5304585900068446, "crossing": "unmarked"}, {"age": 1.5304585900068446, "crossing": "unmarked"}, {"age": 1.9876796714579055, "crossing": "unmarked"}, {"age": 1.9794661190965093, "crossing": "unmarked"}, {"age": 1.9794661190965093, "crossing": "unmarked"}, {"age": 0.7529089664613279, "crossing": "unmarked"}, {"age": 3.436002737850787, "crossing": "unmarked"}, {"age": 0.7529089664613279, "crossing": "unmarked"}, {"age": 3.436002737850787, "crossing": "unmarked"}, {"age": 3.436002737850787, "crossing": "unmarked"}, {"age": 3.436002737850787, "crossing": "unmarked"}, {"age": 0.7529089664613279, "crossing": "unmarked"}, {"age": 0.7529089664613279, "crossing": "unmarked"}, {"age": 1.995893223819302, "crossing": "unmarked"}, {"age": 1.9794661190965093, "crossing": "unmarked"}, {"age": 1.9876796714579055, "crossing": "unmarked"}, {"age": 3.19233401779603, "crossing": "unmarked"}, {"age": 3.19233401779603, "crossing": "unmarked"}, {"age": 3.436002737850787, "crossing": "unmarked"}, {"age": 3.4277891854893907, "crossing": "unmarked"}, {"age": 1.9274469541409993, "crossing": "unmarked"}, {"age": 0.8733744010951403, "crossing": "unmarked"}, {"age": 1.6344969199178645, "crossing": "unmarked"}, {"age": 3.4168377823408624, "crossing": "unmarked"}, {"age": 3.4113620807665983, "crossing": "unmarked"}, {"age": 3.4168377823408624, "crossing": "unmarked"}, {"age": 3.4113620807665983, "crossing": "unmarked"}, {"age": 3.4168377823408624, "crossing": "unmarked"}, {"age": 3.4168377823408624, "crossing": "unmarked"}, {"age": 3.4168377823408624, "crossing": "unmarked"}, {"age": 3.4168377823408624, "crossing": "unmarked"}, {"age": 3.4168377823408624, "crossing": "unmarked"}, {"age": 3.19233401779603, "crossing": "unmarked"}, {"age": 3.4168377823408624, "crossing": "unmarked"}, {"age": 3.4168377823408624, "crossing": "unmarked"}, {"age": 3.4168377823408624, "crossing": "unmarked"}, {"age": 3.4168377823408624, "crossing": "unmarked"}, {"age": 3.4168377823408624, "crossing": "unmarked"}, {"age": 3.4168377823408624, "crossing": "unmarked"}, {"age": 3.4168377823408624, "crossing": "unmarked"}, {"age": 3.4168377823408624, "crossing": "unmarked"}, {"age": 3.4168377823408624, "crossing": "unmarked"}, {"age": 3.4168377823408624, "crossing": "unmarked"}, {"age": 3.4168377823408624, "crossing": "unmarked"}, {"age": 3.4168377823408624, "crossing": "unmarked"}, {"age": 0.8788501026694046, "crossing": "unmarked"}, {"age": 1.9794661190965093, "crossing": "unmarked"}, {"age": 3.2306639288158796, "crossing": "unmarked"}, {"age": 3.2306639288158796, "crossing": "unmarked"}, {"age": 1.9794661190965093, "crossing": "unmarked"}, {"age": 3.1047227926078027, "crossing": "unmarked"}, {"age": 3.4113620807665983, "crossing": "unmarked"}, {"age": 2.132785763175907, "crossing": "unmarked"}, {"age": 2.132785763175907, "crossing": "unmarked"}, {"age": 2.132785763175907, "crossing": "unmarked"}, {"age": 0.8624229979466119, "crossing": "unmarked"}, {"age": 0.8624229979466119, "crossing": "unmarked"}, {"age": 2.132785763175907, "crossing": "unmarked"}, {"age": 2.132785763175907, "crossing": "unmarked"}, {"age": 2.132785763175907, "crossing": "unmarked"}, {"age": 2.132785763175907, "crossing": "unmarked"}, {"age": 2.132785763175907, "crossing": "unmarked"}, {"age": 2.132785763175907, "crossing": "unmarked"}, {"age": 2.132785763175907, "crossing": "unmarked"}, {"age": 2.132785763175907, "crossing": "unmarked"}, {"age": 2.132785763175907, "crossing": "unmarked"}, {"age": 2.132785763175907, "crossing": "unmarked"}, {"age": 2.132785763175907, "crossing": "unmarked"}, {"age": 0.8624229979466119, "crossing": "unmarked"}, {"age": 1.9301848049281314, "crossing": "unmarked"}, {"age": 2.132785763175907, "crossing": "unmarked"}, {"age": 2.132785763175907, "crossing": "unmarked"}, {"age": 2.132785763175907, "crossing": "unmarked"}, {"age": 2.132785763175907, "crossing": "unmarked"}, {"age": 2.132785763175907, "crossing": "unmarked"}, {"age": 0.8624229979466119, "crossing": "unmarked"}, {"age": 2.132785763175907, "crossing": "unmarked"}, {"age": 2.132785763175907, "crossing": "unmarked"}, {"age": 2.132785763175907, "crossing": "unmarked"}, {"age": 2.132785763175907, "crossing": "unmarked"}, {"age": 0.8733744010951403, "crossing": "unmarked"}, {"age": 2.132785763175907, "crossing": "unmarked"}, {"age": 1.949349760438056, "crossing": "unmarked"}, {"age": 3.19233401779603, "crossing": "unmarked"}, {"age": 2.42299794661191, "crossing": "unmarked"}, {"age": 0.974674880219028, "crossing": "unmarked"}, {"age": 2.42299794661191, "crossing": "unmarked"}, {"age": 2.42299794661191, "crossing": "unmarked"}, {"age": 3.4113620807665983, "crossing": "unmarked"}, {"age": 0.8788501026694046, "crossing": "?"}, {"age": 0.8788501026694046, "crossing": "unmarked"}, {"age": 2.42299794661191, "crossing": "unmarked"}, {"age": 3.19233401779603, "crossing": "unmarked"}, {"age": 2.42299794661191, "crossing": "unmarked"}, {"age": 1.9876796714579055, "crossing": "unmarked"}, {"age": 3.4113620807665983, "crossing": "unmarked"}, {"age": 3.4113620807665983, "crossing": "unmarked"}, {"age": 3.405886379192334, "crossing": "unmarked"}, {"age": 0.9582477754962354, "crossing": "unmarked"}, {"age": 0.9582477754962354, "crossing": "unmarked"}, {"age": 3.405886379192334, "crossing": "unmarked"}, {"age": 3.405886379192334, "crossing": "unmarked"}, {"age": 0.9582477754962354, "crossing": "unmarked"}, {"age": 3.405886379192334, "crossing": "unmarked"}, {"age": 0.9582477754962354, "crossing": "unmarked"}, {"age": 3.405886379192334, "crossing": "unmarked"}, {"age": 0.9582477754962354, "crossing": "unmarked"}, {"age": 0.9582477754962354, "crossing": "unmarked"}, {"age": 0.9582477754962354, "crossing": "unmarked"}, {"age": 0.9582477754962354, "crossing": "unmarked"}, {"age": 0.9582477754962354, "crossing": "unmarked"}, {"age": 0.9582477754962354, "crossing": "unmarked"}, {"age": 0.9582477754962354, "crossing": "unmarked"}, {"age": 0.9582477754962354, "crossing": "unmarked"}, {"age": 0.9582477754962354, "crossing": "unmarked"}, {"age": 2.132785763175907, "crossing": "unmarked"}, {"age": 2.132785763175907, "crossing": "unmarked"}, {"age": 2.132785763175907, "crossing": "unmarked"}, {"age": 2.132785763175907, "crossing": "unmarked"}, {"age": 2.132785763175907, "crossing": "unmarked"}, {"age": 2.132785763175907, "crossing": "unmarked"}, {"age": 2.132785763175907, "crossing": "unmarked"}, {"age": 1.514031485284052, "crossing": "unmarked"}, {"age": 1.514031485284052, "crossing": "unmarked"}, {"age": 1.51129363449692, "crossing": "unmarked"}, {"age": 2.132785763175907, "crossing": "unmarked"}, {"age": 2.132785763175907, "crossing": "unmarked"}, {"age": 1.514031485284052, "crossing": "unmarked"}, {"age": 1.514031485284052, "crossing": "unmarked"}, {"age": 1.514031485284052, "crossing": "unmarked"}, {"age": 2.132785763175907, "crossing": "unmarked"}, {"age": 2.132785763175907, "crossing": "unmarked"}, {"age": 0.9582477754962354, "crossing": "unmarked"}, {"age": 0.9582477754962354, "crossing": "unmarked"}, {"age": 3.405886379192334, "crossing": "unmarked"}, {"age": 0.9582477754962354, "crossing": "unmarked"}, {"age": 3.405886379192334, "crossing": "unmarked"}, {"age": 0.9582477754962354, "crossing": "unmarked"}, {"age": 3.405886379192334, "crossing": "unmarked"}, {"age": 3.405886379192334, "crossing": "unmarked"}, {"age": 3.405886379192334, "crossing": "unmarked"}, {"age": 3.405886379192334, "crossing": "unmarked"}, {"age": 3.405886379192334, "crossing": "unmarked"}, {"age": 3.1047227926078027, "crossing": "unmarked"}, {"age": 3.2251882272416155, "crossing": "unmarked"}, {"age": 3.2251882272416155, "crossing": "unmarked"}, {"age": 0.8624229979466119, "crossing": "unmarked"}, {"age": 3.2251882272416155, "crossing": "unmarked"}, {"age": 3.2251882272416155, "crossing": "unmarked"}, {"age": 0.7529089664613279, "crossing": "unmarked"}, {"age": 0.7529089664613279, "crossing": "unmarked"}, {"age": 2.4941820670773445, "crossing": "marked"}, {"age": 2.6967830253251197, "crossing": "unmarked"}, {"age": 2.6967830253251197, "crossing": "unmarked"}, {"age": 1.568788501026694, "crossing": "traffic_signals"}, {"age": 1.568788501026694, "crossing": "marked"}, {"age": 1.538672142368241, "crossing": "unmarked"}, {"age": 2.6967830253251197, "crossing": "marked"}, {"age": 2.6967830253251197, "crossing": "marked"}, {"age": 1.620807665982204, "crossing": "marked"}, {"age": 1.620807665982204, "crossing": "marked"}, {"age": 1.7084188911704312, "crossing": "unmarked"}, {"age": 1.270362765229295, "crossing": "marked"}, {"age": 1.270362765229295, "crossing": "?"}, {"age": 1.270362765229295, "crossing": "marked"}, {"age": 2.6940451745379876, "crossing": "marked"}, {"age": 2.6940451745379876, "crossing": "marked"}, {"age": 2.6940451745379876, "crossing": "?"}, {"age": 2.6940451745379876, "crossing": "marked"}, {"age": 0.7529089664613279, "crossing": "unmarked"}, {"age": 0.7529089664613279, "crossing": "unmarked"}, {"age": 0.7529089664613279, "crossing": "unmarked"}, {"age": 0.7529089664613279, "crossing": "unmarked"}, {"age": 0.7529089664613279, "crossing": "unmarked"}, {"age": 0.5968514715947981, "crossing": "unmarked"}, {"age": 1.273100616016427, "crossing": "marked"}, {"age": 1.270362765229295, "crossing": "unmarked"}, {"age": 1.270362765229295, "crossing": "unmarked"}, {"age": 1.270362765229295, "crossing": "unmarked"}, {"age": 1.270362765229295, "crossing": "unmarked"}, {"age": 1.270362765229295, "crossing": "unmarked"}, {"age": 1.270362765229295, "crossing": "?"}, {"age": 1.273100616016427, "crossing": "unmarked"}, {"age": 1.273100616016427, "crossing": "unmarked"}, {"age": 1.2238193018480492, "crossing": "?"}, {"age": 1.2238193018480492, "crossing": "unmarked"}, {"age": 1.516769336071184, "crossing": "marked"}, {"age": 1.270362765229295, "crossing": "marked"}, {"age": 1.568788501026694, "crossing": "marked"}, {"age": 2.132785763175907, "crossing": "?"}, {"age": 1.270362765229295, "crossing": "marked"}, {"age": 1.270362765229295, "crossing": "?"}, {"age": 1.568788501026694, "crossing": "unmarked"}, {"age": 1.5359342915811087, "crossing": "unmarked"}, {"age": 1.273100616016427, "crossing": "unmarked"}, {"age": 1.2238193018480492, "crossing": "unmarked"}, {"age": 1.2238193018480492, "crossing": "marked"}, {"age": 1.516769336071184, "crossing": "unmarked"}, {"age": 1.270362765229295, "crossing": "unmarked"}, {"age": 1.516769336071184, "crossing": "unmarked"}, {"age": 1.2238193018480492, "crossing": "?"}, {"age": 1.270362765229295, "crossing": "?"}, {"age": 1.270362765229295, "crossing": "marked"}, {"age": 1.5797399041752225, "crossing": "marked"}, {"age": 1.273100616016427, "crossing": "marked"}, {"age": 1.568788501026694, "crossing": "unmarked"}, {"age": 2.652977412731006, "crossing": "?"}, {"age": 2.650239561943874, "crossing": "marked"}, {"age": 2.650239561943874, "crossing": "marked"}, {"age": 2.650239561943874, "crossing": "marked"}, {"age": 2.650239561943874, "crossing": "marked"}, {"age": 2.650239561943874, "crossing": "marked"}, {"age": 1.5797399041752225, "crossing": "marked"}, {"age": 1.270362765229295, "crossing": "marked"}, {"age": 1.270362765229295, "crossing": "marked"}, {"age": 1.270362765229295, "crossing": "marked"}, {"age": 1.270362765229295, "crossing": "marked"}, {"age": 1.270362765229295, "crossing": "?"}, {"age": 1.5359342915811087, "crossing": "marked"}, {"age": 1.5359342915811087, "crossing": "marked"}, {"age": 1.270362765229295, "crossing": "marked"}, {"age": 1.270362765229295, "crossing": "marked"}, {"age": 1.270362765229295, "crossing": "?"}, {"age": 1.270362765229295, "crossing": "?"}, {"age": 1.270362765229295, "crossing": "?"}, {"age": 1.273100616016427, "crossing": "?"}, {"age": 1.270362765229295, "crossing": "marked"}, {"age": 1.270362765229295, "crossing": "?"}, {"age": 1.270362765229295, "crossing": "?"}, {"age": 1.270362765229295, "crossing": "?"}, {"age": 1.270362765229295, "crossing": "?"}, {"age": 2.524298425735797, "crossing": "unmarked"}, {"age": 2.524298425735797, "crossing": "unmarked"}, {"age": 2.524298425735797, "crossing": "unmarked"}, {"age": 2.524298425735797, "crossing": "unmarked"}, {"age": 2.524298425735797, "crossing": "unmarked"}, {"age": 2.524298425735797, "crossing": "unmarked"}, {"age": 2.4750171115674195, "crossing": "unmarked"}, {"age": 2.4750171115674195, "crossing": "unmarked"}, {"age": 2.4750171115674195, "crossing": "unmarked"}, {"age": 2.4750171115674195, "crossing": "unmarked"}, {"age": 2.4750171115674195, "crossing": "unmarked"}, {"age": 2.4750171115674195, "crossing": "unmarked"}, {"age": 2.4750171115674195, "crossing": "unmarked"}, {"age": 2.4750171115674195, "crossing": "unmarked"}, {"age": 2.4750171115674195, "crossing": "unmarked"}, {"age": 2.4750171115674195, "crossing": "unmarked"}, {"age": 2.4750171115674195, "crossing": "unmarked"}, {"age": 2.4750171115674195, "crossing": "unmarked"}, {"age": 2.4750171115674195, "crossing": "unmarked"}, {"age": 2.4750171115674195, "crossing": "unmarked"}, {"age": 2.4750171115674195, "crossing": "unmarked"}, {"age": 2.4750171115674195, "crossing": "unmarked"}, {"age": 2.4750171115674195, "crossing": "unmarked"}, {"age": 2.4750171115674195, "crossing": "unmarked"}, {"age": 2.4750171115674195, "crossing": "unmarked"}, {"age": 2.4750171115674195, "crossing": "unmarked"}, {"age": 2.4750171115674195, "crossing": "unmarked"}, {"age": 2.4750171115674195, "crossing": "unmarked"}, {"age": 2.4750171115674195, "crossing": "unmarked"}, {"age": 2.4750171115674195, "crossing": "unmarked"}, {"age": 2.4750171115674195, "crossing": "unmarked"}, {"age": 2.4750171115674195, "crossing": "unmarked"}, {"age": 2.521560574948665, "crossing": "unmarked"}, {"age": 2.521560574948665, "crossing": "unmarked"}, {"age": 2.132785763175907, "crossing": "unmarked"}, {"age": 2.132785763175907, "crossing": "unmarked"}, {"age": 1.6098562628336757, "crossing": "traffic_signals"}, {"age": 1.3360711841204653, "crossing": "traffic_signals"}, {"age": 0.8733744010951403, "crossing": "unmarked"}, {"age": 2.5023956194387407, "crossing": "unmarked"}, {"age": 2.5023956194387407, "crossing": "unmarked"}, {"age": 2.132785763175907, "crossing": "unmarked"}, {"age": 2.132785763175907, "crossing": "unmarked"}, {"age": 2.132785763175907, "crossing": "unmarked"}, {"age": 2.132785763175907, "crossing": "unmarked"}, {"age": 1.9301848049281314, "crossing": "unmarked"}, {"age": 2.132785763175907, "crossing": "unmarked"}, {"age": 1.9301848049281314, "crossing": "unmarked"}, {"age": 1.514031485284052, "crossing": "unmarked"}, {"age": 1.9301848049281314, "crossing": "unmarked"}, {"age": 1.949349760438056, "crossing": "unmarked"}, {"age": 2.132785763175907, "crossing": "unmarked"}, {"age": 2.132785763175907, "crossing": "unmarked"}, {"age": 0.974674880219028, "crossing": "unmarked"}, {"age": 0.974674880219028, "crossing": "unmarked"}, {"age": 2.132785763175907, "crossing": "unmarked"}, {"age": 2.132785763175907, "crossing": "unmarked"}, {"age": 2.132785763175907, "crossing": "unmarked"}, {"age": 2.132785763175907, "crossing": "unmarked"}, {"age": 2.132785763175907, "crossing": "unmarked"}, {"age": 2.132785763175907, "crossing": "unmarked"}, {"age": 2.132785763175907, "crossing": "unmarked"}, {"age": 1.6454483230663928, "crossing": "unmarked"}, {"age": 0.7529089664613279, "crossing": "unmarked"}, {"age": 0.7529089664613279, "crossing": "unmarked"}, {"age": 2.4640657084188913, "crossing": "unmarked"}, {"age": 2.4640657084188913, "crossing": "unmarked"}, {"age": 2.4640657084188913, "crossing": "unmarked"}, {"age": 2.458590006844627, "crossing": "?"}, {"age": 2.458590006844627, "crossing": "?"}, {"age": 2.458590006844627, "crossing": "?"}, {"age": 2.455852156057495, "crossing": "unmarked"}, {"age": 1.516769336071184, "crossing": "unmarked"}, {"age": 1.516769336071184, "crossing": "unmarked"}, {"age": 2.132785763175907, "crossing": "?"}, {"age": 2.132785763175907, "crossing": "?"}, {"age": 2.132785763175907, "crossing": "marked"}, {"age": 2.42299794661191, "crossing": "unmarked"}, {"age": 2.42299794661191, "crossing": "unmarked"}, {"age": 1.2292950034223136, "crossing": "unmarked"}, {"age": 0.7529089664613279, "crossing": "traffic_signals"}, {"age": 0.5776865160848734, "crossing": "uncontrolled"}, {"age": 2.099931553730322, "crossing": "unmarked"}, {"age": 2.0752908966461328, "crossing": "marked"}, {"age": 2.0752908966461328, "crossing": "marked"}, {"age": 2.0752908966461328, "crossing": "marked"}, {"age": 2.0752908966461328, "crossing": "marked"}, {"age": 2.0533880903490758, "crossing": "marked"}, {"age": 2.0533880903490758, "crossing": "marked"}, {"age": 0.12046543463381246, "crossing": "unmarked"}, {"age": 1.9739904175222451, "crossing": "?"}, {"age": 1.9739904175222451, "crossing": "?"}, {"age": 1.9739904175222451, "crossing": "?"}, {"age": 1.9739904175222451, "crossing": "?"}, {"age": 1.9739904175222451, "crossing": "?"}, {"age": 1.9739904175222451, "crossing": "?"}, {"age": 1.9739904175222451, "crossing": "?"}, {"age": 1.9739904175222451, "crossing": "?"}, {"age": 1.9739904175222451, "crossing": "?"}, {"age": 1.9739904175222451, "crossing": "?"}, {"age": 1.9739904175222451, "crossing": "?"}, {"age": 1.9739904175222451, "crossing": "?"}, {"age": 1.9739904175222451, "crossing": "?"}, {"age": 1.9739904175222451, "crossing": "?"}, {"age": 1.9739904175222451, "crossing": "?"}, {"age": 1.9739904175222451, "crossing": "?"}, {"age": 1.9739904175222451, "crossing": "?"}, {"age": 1.9739904175222451, "crossing": "?"}, {"age": 1.9739904175222451, "crossing": "?"}, {"age": 1.9739904175222451, "crossing": "?"}, {"age": 1.9739904175222451, "crossing": "?"}, {"age": 1.9739904175222451, "crossing": "?"}, {"age": 1.9739904175222451, "crossing": "?"}, {"age": 1.9739904175222451, "crossing": "?"}, {"age": 1.9739904175222451, "crossing": "?"}, {"age": 1.9739904175222451, "crossing": "?"}, {"age": 1.9739904175222451, "crossing": "?"}, {"age": 1.9739904175222451, "crossing": "?"}, {"age": 0.4134154688569473, "crossing": "?"}, {"age": 0.4134154688569473, "crossing": "?"}, {"age": 1.9739904175222451, "crossing": "?"}, {"age": 1.9739904175222451, "crossing": "?"}, {"age": 1.9739904175222451, "crossing": "?"}, {"age": 1.9739904175222451, "crossing": "?"}, {"age": 1.9739904175222451, "crossing": "?"}, {"age": 1.9739904175222451, "crossing": "?"}, {"age": 1.9739904175222451, "crossing": "?"}, {"age": 1.9739904175222451, "crossing": "?"}, {"age": 1.9739904175222451, "crossing": "?"}, {"age": 1.9739904175222451, "crossing": "?"}, {"age": 1.9739904175222451, "crossing": "?"}, {"age": 1.9739904175222451, "crossing": "?"}, {"age": 1.9739904175222451, "crossing": "?"}, {"age": 1.9739904175222451, "crossing": "?"}, {"age": 1.9739904175222451, "crossing": "?"}, {"age": 1.9739904175222451, "crossing": "?"}, {"age": 1.9739904175222451, "crossing": "?"}, {"age": 1.9739904175222451, "crossing": "?"}, {"age": 1.9739904175222451, "crossing": "?"}, {"age": 1.9739904175222451, "crossing": "?"}, {"age": 1.9739904175222451, "crossing": "?"}, {"age": 1.9739904175222451, "crossing": "?"}, {"age": 1.9739904175222451, "crossing": "?"}, {"age": 1.9739904175222451, "crossing": "?"}, {"age": 1.9739904175222451, "crossing": "?"}, {"age": 1.9739904175222451, "crossing": "?"}, {"age": 1.9739904175222451, "crossing": "?"}, {"age": 1.9739904175222451, "crossing": "?"}, {"age": 1.9739904175222451, "crossing": "?"}, {"age": 1.9739904175222451, "crossing": "?"}, {"age": 1.9739904175222451, "crossing": "?"}, {"age": 1.9739904175222451, "crossing": "?"}, {"age": 1.9739904175222451, "crossing": "?"}, {"age": 1.9739904175222451, "crossing": "?"}, {"age": 1.9739904175222451, "crossing": "?"}, {"age": 1.9739904175222451, "crossing": "?"}, {"age": 1.9739904175222451, "crossing": "?"}, {"age": 1.9739904175222451, "crossing": "?"}, {"age": 1.9739904175222451, "crossing": "?"}, {"age": 1.9739904175222451, "crossing": "?"}, {"age": 1.9739904175222451, "crossing": "?"}, {"age": 1.9739904175222451, "crossing": "?"}, {"age": 1.9739904175222451, "crossing": "?"}, {"age": 1.9739904175222451, "crossing": "?"}, {"age": 1.9739904175222451, "crossing": "?"}, {"age": 1.9739904175222451, "crossing": "?"}, {"age": 1.9739904175222451, "crossing": "?"}, {"age": 1.9739904175222451, "crossing": "?"}, {"age": 1.9739904175222451, "crossing": "?"}, {"age": 1.9739904175222451, "crossing": "?"}, {"age": 1.9739904175222451, "crossing": "?"}, {"age": 1.9739904175222451, "crossing": "?"}, {"age": 1.9739904175222451, "crossing": "?"}, {"age": 1.9739904175222451, "crossing": "?"}, {"age": 1.9739904175222451, "crossing": "?"}, {"age": 1.9739904175222451, "crossing": "?"}, {"age": 1.9739904175222451, "crossing": "?"}, {"age": 1.9739904175222451, "crossing": "?"}, {"age": 1.9739904175222451, "crossing": "?"}, {"age": 1.9739904175222451, "crossing": "?"}, {"age": 1.9739904175222451, "crossing": "?"}, {"age": 1.9739904175222451, "crossing": "?"}, {"age": 1.9739904175222451, "crossing": "?"}, {"age": 1.9739904175222451, "crossing": "?"}, {"age": 1.9739904175222451, "crossing": "?"}, {"age": 1.9739904175222451, "crossing": "?"}, {"age": 1.9739904175222451, "crossing": "?"}, {"age": 1.9739904175222451, "crossing": "?"}, {"age": 1.9739904175222451, "crossing": "?"}, {"age": 1.9739904175222451, "crossing": "?"}, {"age": 1.9739904175222451, "crossing": "?"}, {"age": 1.9739904175222451, "crossing": "?"}, {"age": 1.9739904175222451, "crossing": "?"}, {"age": 1.9739904175222451, "crossing": "?"}, {"age": 0.33127994524298426, "crossing": "?"}, {"age": 1.9739904175222451, "crossing": "?"}, {"age": 1.9739904175222451, "crossing": "?"}, {"age": 1.9739904175222451, "crossing": "?"}, {"age": 1.9739904175222451, "crossing": "?"}, {"age": 1.9739904175222451, "crossing": "?"}, {"age": 1.9739904175222451, "crossing": "?"}, {"age": 1.9739904175222451, "crossing": "?"}, {"age": 1.9739904175222451, "crossing": "?"}, {"age": 1.9739904175222451, "crossing": "?"}, {"age": 1.9739904175222451, "crossing": "?"}, {"age": 1.9739904175222451, "crossing": "?"}, {"age": 1.9739904175222451, "crossing": "?"}, {"age": 1.9739904175222451, "crossing": "?"}, {"age": 1.9739904175222451, "crossing": "?"}, {"age": 1.9739904175222451, "crossing": "?"}, {"age": 1.2073921971252566, "crossing": "?"}, {"age": 1.9739904175222451, "crossing": "?"}, {"age": 1.5879534565366187, "crossing": "?"}, {"age": 0.29842573579739906, "crossing": "?"}, {"age": 1.9739904175222451, "crossing": "?"}, {"age": 0.29842573579739906, "crossing": "?"}, {"age": 1.9739904175222451, "crossing": "?"}, {"age": 1.9739904175222451, "crossing": "?"}, {"age": 1.5852156057494866, "crossing": "?"}, {"age": 1.5879534565366187, "crossing": "?"}, {"age": 1.9739904175222451, "crossing": "?"}, {"age": 1.9739904175222451, "crossing": "?"}, {"age": 1.9739904175222451, "crossing": "?"}, {"age": 1.9739904175222451, "crossing": "?"}, {"age": 1.9739904175222451, "crossing": "?"}, {"age": 1.9739904175222451, "crossing": "?"}, {"age": 1.9739904175222451, "crossing": "?"}, {"age": 1.9739904175222451, "crossing": "?"}, {"age": 1.9739904175222451, "crossing": "?"}, {"age": 1.9739904175222451, "crossing": "?"}, {"age": 1.9739904175222451, "crossing": "?"}, {"age": 1.9739904175222451, "crossing": "?"}, {"age": 1.9739904175222451, "crossing": "?"}, {"age": 1.9739904175222451, "crossing": "?"}, {"age": 1.9739904175222451, "crossing": "?"}, {"age": 1.9739904175222451, "crossing": "?"}, {"age": 1.9739904175222451, "crossing": "?"}, {"age": 1.9739904175222451, "crossing": "?"}, {"age": 1.9739904175222451, "crossing": "?"}, {"age": 1.9739904175222451, "crossing": "?"}, {"age": 1.9739904175222451, "crossing": "?"}, {"age": 1.9739904175222451, "crossing": "?"}, {"age": 1.9739904175222451, "crossing": "?"}, {"age": 1.9739904175222451, "crossing": "?"}, {"age": 1.9739904175222451, "crossing": "?"}, {"age": 1.9739904175222451, "crossing": "?"}, {"age": 1.9739904175222451, "crossing": "?"}, {"age": 1.9739904175222451, "crossing": "?"}, {"age": 1.9739904175222451, "crossing": "?"}, {"age": 1.9739904175222451, "crossing": "?"}, {"age": 1.9739904175222451, "crossing": "?"}, {"age": 1.9739904175222451, "crossing": "?"}, {"age": 1.9739904175222451, "crossing": "?"}, {"age": 1.9739904175222451, "crossing": "?"}, {"age": 1.9739904175222451, "crossing": "?"}, {"age": 1.9739904175222451, "crossing": "?"}, {"age": 1.9739904175222451, "crossing": "?"}, {"age": 1.2566735112936345, "crossing": "?"}, {"age": 0.33127994524298426, "crossing": "?"}, {"age": 1.9739904175222451, "crossing": "?"}, {"age": 1.2073921971252566, "crossing": "?"}, {"age": 1.9739904175222451, "crossing": "?"}, {"age": 1.9739904175222451, "crossing": "?"}, {"age": 0.9253935660506503, "crossing": "?"}, {"age": 1.9739904175222451, "crossing": "?"}, {"age": 1.9739904175222451, "crossing": "?"}, {"age": 1.9739904175222451, "crossing": "?"}, {"age": 1.9739904175222451, "crossing": "?"}, {"age": 1.9739904175222451, "crossing": "?"}, {"age": 1.9739904175222451, "crossing": "?"}, {"age": 1.9739904175222451, "crossing": "?"}, {"age": 1.9739904175222451, "crossing": "?"}, {"age": 1.9739904175222451, "crossing": "?"}, {"age": 1.9739904175222451, "crossing": "?"}, {"age": 0.29842573579739906, "crossing": "?"}, {"age": 1.9739904175222451, "crossing": "?"}, {"age": 1.9739904175222451, "crossing": "?"}, {"age": 1.9739904175222451, "crossing": "?"}, {"age": 1.9739904175222451, "crossing": "?"}, {"age": 1.9739904175222451, "crossing": "?"}, {"age": 1.9739904175222451, "crossing": "?"}, {"age": 1.9739904175222451, "crossing": "?"}, {"age": 1.9739904175222451, "crossing": "?"}, {"age": 1.9739904175222451, "crossing": "?"}, {"age": 1.9739904175222451, "crossing": "?"}, {"age": 1.9739904175222451, "crossing": "?"}, {"age": 1.9739904175222451, "crossing": "?"}, {"age": 1.9739904175222451, "crossing": "?"}, {"age": 1.9739904175222451, "crossing": "?"}, {"age": 1.9739904175222451, "crossing": "?"}, {"age": 1.9739904175222451, "crossing": "?"}, {"age": 1.9739904175222451, "crossing": "?"}, {"age": 1.9739904175222451, "crossing": "?"}, {"age": 1.9739904175222451, "crossing": "?"}, {"age": 0.4271047227926078, "crossing": "?"}, {"age": 1.9739904175222451, "crossing": "?"}, {"age": 1.9739904175222451, "crossing": "?"}, {"age": 1.2073921971252566, "crossing": "?"}, {"age": 1.9739904175222451, "crossing": "?"}, {"age": 1.9739904175222451, "crossing": "?"}, {"age": 1.2073921971252566, "crossing": "?"}, {"age": 1.9739904175222451, "crossing": "?"}, {"age": 1.9739904175222451, "crossing": "?"}, {"age": 1.9739904175222451, "crossing": "?"}, {"age": 1.9739904175222451, "crossing": "?"}, {"age": 1.9739904175222451, "crossing": "?"}, {"age": 1.9739904175222451, "crossing": "?"}, {"age": 1.5879534565366187, "crossing": "?"}, {"age": 1.9739904175222451, "crossing": "?"}, {"age": 1.9739904175222451, "crossing": "?"}, {"age": 1.9739904175222451, "crossing": "?"}, {"age": 1.9739904175222451, "crossing": "?"}, {"age": 0.33127994524298426, "crossing": "?"}, {"age": 1.9739904175222451, "crossing": "?"}, {"age": 1.9739904175222451, "crossing": "?"}, {"age": 1.9739904175222451, "crossing": "?"}, {"age": 1.9739904175222451, "crossing": "?"}, {"age": 1.9739904175222451, "crossing": "?"}, {"age": 1.9739904175222451, "crossing": "?"}, {"age": 1.9739904175222451, "crossing": "?"}, {"age": 1.9739904175222451, "crossing": "?"}, {"age": 1.9739904175222451, "crossing": "?"}, {"age": 1.9739904175222451, "crossing": "?"}, {"age": 1.9739904175222451, "crossing": "?"}, {"age": 1.9739904175222451, "crossing": "?"}, {"age": 1.9739904175222451, "crossing": "?"}, {"age": 1.9739904175222451, "crossing": "?"}, {"age": 1.9739904175222451, "crossing": "?"}, {"age": 1.9739904175222451, "crossing": "?"}, {"age": 1.9739904175222451, "crossing": "?"}, {"age": 1.9739904175222451, "crossing": "?"}, {"age": 1.9739904175222451, "crossing": "?"}, {"age": 1.9739904175222451, "crossing": "?"}, {"age": 1.9739904175222451, "crossing": "?"}, {"age": 1.9739904175222451, "crossing": "?"}, {"age": 1.9739904175222451, "crossing": "?"}, {"age": 1.9739904175222451, "crossing": "?"}, {"age": 1.9739904175222451, "crossing": "?"}, {"age": 1.9739904175222451, "crossing": "?"}, {"age": 1.9739904175222451, "crossing": "?"}, {"age": 1.9739904175222451, "crossing": "?"}, {"age": 1.9739904175222451, "crossing": "?"}, {"age": 1.9739904175222451, "crossing": "?"}, {"age": 1.9739904175222451, "crossing": "?"}, {"age": 1.9739904175222451, "crossing": "?"}, {"age": 1.9739904175222451, "crossing": "?"}, {"age": 1.9739904175222451, "crossing": "?"}, {"age": 1.9739904175222451, "crossing": "?"}, {"age": 1.9739904175222451, "crossing": "?"}, {"age": 1.9739904175222451, "crossing": "?"}, {"age": 1.9739904175222451, "crossing": "?"}, {"age": 1.9739904175222451, "crossing": "?"}, {"age": 1.9739904175222451, "crossing": "?"}, {"age": 1.9739904175222451, "crossing": "?"}, {"age": 1.9739904175222451, "crossing": "?"}, {"age": 1.7166324435318274, "crossing": "?"}, {"age": 1.9739904175222451, "crossing": "?"}, {"age": 1.3059548254620124, "crossing": "uncontrolled"}, {"age": 1.9739904175222451, "crossing": "?"}, {"age": 1.9739904175222451, "crossing": "?"}, {"age": 0.9253935660506503, "crossing": "?"}, {"age": 1.9739904175222451, "crossing": "?"}, {"age": 0.33127994524298426, "crossing": "?"}, {"age": 1.9739904175222451, "crossing": "?"}, {"age": 1.9739904175222451, "crossing": "?"}, {"age": 1.9739904175222451, "crossing": "?"}, {"age": 1.9739904175222451, "crossing": "?"}, {"age": 1.9739904175222451, "crossing": "?"}, {"age": 1.5550992470910336, "crossing": "?"}, {"age": 0.7885010266940452, "crossing": "?"}, {"age": 1.9739904175222451, "crossing": "?"}, {"age": 1.9739904175222451, "crossing": "?"}, {"age": 1.9739904175222451, "crossing": "?"}, {"age": 1.9739904175222451, "crossing": "?"}, {"age": 1.9739904175222451, "crossing": "?"}, {"age": 1.9739904175222451, "crossing": "?"}, {"age": 1.9739904175222451, "crossing": "?"}, {"age": 1.9739904175222451, "crossing": "?"}, {"age": 1.9739904175222451, "crossing": "?"}, {"age": 1.9739904175222451, "crossing": "?"}, {"age": 1.9739904175222451, "crossing": "?"}, {"age": 1.9739904175222451, "crossing": "?"}, {"age": 1.9739904175222451, "crossing": "?"}, {"age": 1.9739904175222451, "crossing": "?"}, {"age": 1.9739904175222451, "crossing": "?"}, {"age": 1.9739904175222451, "crossing": "?"}, {"age": 1.9739904175222451, "crossing": "?"}, {"age": 1.9739904175222451, "crossing": "?"}, {"age": 1.9739904175222451, "crossing": "?"}, {"age": 1.9739904175222451, "crossing": "?"}, {"age": 1.9739904175222451, "crossing": "?"}, {"age": 1.9739904175222451, "crossing": "?"}, {"age": 1.9739904175222451, "crossing": "?"}, {"age": 1.9739904175222451, "crossing": "?"}, {"age": 1.9739904175222451, "crossing": "?"}, {"age": 1.9739904175222451, "crossing": "?"}, {"age": 1.9739904175222451, "crossing": "?"}, {"age": 1.9739904175222451, "crossing": "?"}, {"age": 1.9739904175222451, "crossing": "?"}, {"age": 1.9739904175222451, "crossing": "?"}, {"age": 1.9739904175222451, "crossing": "?"}, {"age": 1.9739904175222451, "crossing": "?"}, {"age": 1.9739904175222451, "crossing": "?"}, {"age": 1.9739904175222451, "crossing": "?"}, {"age": 1.9739904175222451, "crossing": "?"}, {"age": 1.9739904175222451, "crossing": "?"}, {"age": 1.9739904175222451, "crossing": "?"}, {"age": 1.9739904175222451, "crossing": "?"}, {"age": 1.9739904175222451, "crossing": "?"}, {"age": 1.9739904175222451, "crossing": "?"}, {"age": 1.9739904175222451, "crossing": "?"}, {"age": 1.9739904175222451, "crossing": "?"}, {"age": 1.9739904175222451, "crossing": "?"}, {"age": 1.9739904175222451, "crossing": "?"}, {"age": 1.9739904175222451, "crossing": "?"}, {"age": 1.9739904175222451, "crossing": "?"}, {"age": 1.9739904175222451, "crossing": "?"}, {"age": 1.9739904175222451, "crossing": "?"}, {"age": 1.9739904175222451, "crossing": "?"}, {"age": 1.9739904175222451, "crossing": "?"}, {"age": 1.9739904175222451, "crossing": "?"}, {"age": 1.9739904175222451, "crossing": "?"}, {"age": 1.9739904175222451, "crossing": "?"}, {"age": 1.9739904175222451, "crossing": "?"}, {"age": 1.9739904175222451, "crossing": "?"}, {"age": 1.9739904175222451, "crossing": "?"}, {"age": 1.9739904175222451, "crossing": "?"}, {"age": 1.9739904175222451, "crossing": "?"}, {"age": 1.9739904175222451, "crossing": "?"}, {"age": 1.9739904175222451, "crossing": "?"}, {"age": 1.9739904175222451, "crossing": "?"}, {"age": 1.9739904175222451, "crossing": "?"}, {"age": 1.9739904175222451, "crossing": "?"}, {"age": 1.9739904175222451, "crossing": "?"}, {"age": 1.9739904175222451, "crossing": "?"}, {"age": 1.9739904175222451, "crossing": "?"}, {"age": 1.9739904175222451, "crossing": "?"}, {"age": 1.9739904175222451, "crossing": "?"}, {"age": 1.9739904175222451, "crossing": "?"}, {"age": 1.9739904175222451, "crossing": "?"}, {"age": 1.9739904175222451, "crossing": "?"}, {"age": 0.4134154688569473, "crossing": "?"}, {"age": 0.4134154688569473, "crossing": "?"}, {"age": 1.9739904175222451, "crossing": "?"}, {"age": 1.9739904175222451, "crossing": "?"}, {"age": 1.9739904175222451, "crossing": "?"}, {"age": 1.9739904175222451, "crossing": "?"}, {"age": 1.9739904175222451, "crossing": "?"}, {"age": 1.9739904175222451, "crossing": "?"}, {"age": 1.9739904175222451, "crossing": "?"}, {"age": 1.9739904175222451, "crossing": "?"}, {"age": 1.9739904175222451, "crossing": "?"}, {"age": 1.9739904175222451, "crossing": "?"}, {"age": 1.9739904175222451, "crossing": "?"}, {"age": 1.9739904175222451, "crossing": "?"}, {"age": 1.9739904175222451, "crossing": "?"}, {"age": 1.9739904175222451, "crossing": "?"}, {"age": 1.9739904175222451, "crossing": "?"}, {"age": 1.9739904175222451, "crossing": "?"}, {"age": 1.9739904175222451, "crossing": "?"}, {"age": 1.9739904175222451, "crossing": "?"}, {"age": 1.9739904175222451, "crossing": "?"}, {"age": 1.9739904175222451, "crossing": "?"}, {"age": 1.9739904175222451, "crossing": "?"}, {"age": 1.9739904175222451, "crossing": "?"}, {"age": 1.9739904175222451, "crossing": "?"}, {"age": 1.9739904175222451, "crossing": "?"}, {"age": 1.9739904175222451, "crossing": "?"}, {"age": 1.9739904175222451, "crossing": "?"}, {"age": 1.9739904175222451, "crossing": "?"}, {"age": 1.9739904175222451, "crossing": "?"}, {"age": 1.9739904175222451, "crossing": "?"}, {"age": 1.9739904175222451, "crossing": "?"}, {"age": 1.9739904175222451, "crossing": "?"}, {"age": 1.9739904175222451, "crossing": "?"}, {"age": 1.9739904175222451, "crossing": "?"}, {"age": 1.9739904175222451, "crossing": "?"}, {"age": 1.9739904175222451, "crossing": "?"}, {"age": 1.9739904175222451, "crossing": "?"}, {"age": 1.9739904175222451, "crossing": "?"}, {"age": 1.9739904175222451, "crossing": "?"}, {"age": 1.9739904175222451, "crossing": "?"}, {"age": 1.9739904175222451, "crossing": "?"}, {"age": 1.9739904175222451, "crossing": "?"}, {"age": 0.7885010266940452, "crossing": "uncontrolled"}, {"age": 1.9739904175222451, "crossing": "?"}, {"age": 1.9739904175222451, "crossing": "?"}, {"age": 1.9739904175222451, "crossing": "?"}, {"age": 1.9739904175222451, "crossing": "?"}, {"age": 1.9739904175222451, "crossing": "?"}, {"age": 1.9739904175222451, "crossing": "?"}, {"age": 1.9739904175222451, "crossing": "?"}, {"age": 1.9739904175222451, "crossing": "?"}, {"age": 1.9739904175222451, "crossing": "?"}, {"age": 1.9739904175222451, "crossing": "?"}, {"age": 1.2566735112936345, "crossing": "?"}, {"age": 1.9739904175222451, "crossing": "?"}, {"age": 1.9739904175222451, "crossing": "?"}, {"age": 1.9739904175222451, "crossing": "?"}, {"age": 1.9739904175222451, "crossing": "?"}, {"age": 1.9739904175222451, "crossing": "?"}, {"age": 1.9739904175222451, "crossing": "?"}, {"age": 1.9739904175222451, "crossing": "?"}, {"age": 1.9739904175222451, "crossing": "?"}, {"age": 1.9739904175222451, "crossing": "?"}, {"age": 1.9739904175222451, "crossing": "?"}, {"age": 1.9739904175222451, "crossing": "?"}, {"age": 1.9739904175222451, "crossing": "?"}, {"age": 1.9739904175222451, "crossing": "?"}, {"age": 1.9739904175222451, "crossing": "?"}, {"age": 1.9739904175222451, "crossing": "?"}, {"age": 1.9739904175222451, "crossing": "?"}, {"age": 1.9739904175222451, "crossing": "?"}, {"age": 1.9739904175222451, "crossing": "?"}, {"age": 1.9739904175222451, "crossing": "?"}, {"age": 1.9739904175222451, "crossing": "?"}, {"age": 1.9739904175222451, "crossing": "?"}, {"age": 1.9739904175222451, "crossing": "?"}, {"age": 1.9739904175222451, "crossing": "?"}, {"age": 1.9739904175222451, "crossing": "?"}, {"age": 1.9739904175222451, "crossing": "?"}, {"age": 1.9739904175222451, "crossing": "?"}, {"age": 1.9739904175222451, "crossing": "?"}, {"age": 1.9739904175222451, "crossing": "?"}, {"age": 1.9739904175222451, "crossing": "?"}, {"age": 1.9739904175222451, "crossing": "?"}, {"age": 1.9739904175222451, "crossing": "?"}, {"age": 1.9739904175222451, "crossing": "?"}, {"age": 1.9739904175222451, "crossing": "?"}, {"age": 1.9739904175222451, "crossing": "?"}, {"age": 1.9739904175222451, "crossing": "?"}, {"age": 0.4134154688569473, "crossing": "?"}, {"age": 1.9739904175222451, "crossing": "?"}, {"age": 1.9739904175222451, "crossing": "?"}, {"age": 1.9739904175222451, "crossing": "?"}, {"age": 1.9739904175222451, "crossing": "?"}, {"age": 1.9739904175222451, "crossing": "?"}, {"age": 1.9739904175222451, "crossing": "?"}, {"age": 1.9739904175222451, "crossing": "?"}, {"age": 1.9739904175222451, "crossing": "?"}, {"age": 1.9739904175222451, "crossing": "?"}, {"age": 1.9739904175222451, "crossing": "?"}, {"age": 1.9739904175222451, "crossing": "?"}, {"age": 1.9739904175222451, "crossing": "?"}, {"age": 1.9739904175222451, "crossing": "?"}, {"age": 0.29842573579739906, "crossing": "?"}, {"age": 1.9739904175222451, "crossing": "?"}, {"age": 1.9739904175222451, "crossing": "?"}, {"age": 1.9739904175222451, "crossing": "?"}, {"age": 1.9739904175222451, "crossing": "?"}, {"age": 0.29842573579739906, "crossing": "?"}, {"age": 1.9739904175222451, "crossing": "?"}, {"age": 1.9739904175222451, "crossing": "?"}, {"age": 1.9739904175222451, "crossing": "?"}, {"age": 1.9739904175222451, "crossing": "?"}, {"age": 1.9739904175222451, "crossing": "?"}, {"age": 1.9739904175222451, "crossing": "?"}, {"age": 1.9739904175222451, "crossing": "?"}, {"age": 1.5852156057494866, "crossing": "?"}, {"age": 1.9739904175222451, "crossing": "?"}, {"age": 1.5852156057494866, "crossing": "?"}, {"age": 1.9739904175222451, "crossing": "?"}, {"age": 1.9739904175222451, "crossing": "?"}, {"age": 1.9739904175222451, "crossing": "?"}, {"age": 1.9739904175222451, "crossing": "?"}, {"age": 1.9739904175222451, "crossing": "?"}, {"age": 1.9739904175222451, "crossing": "?"}, {"age": 1.9739904175222451, "crossing": "?"}, {"age": 1.9739904175222451, "crossing": "?"}, {"age": 1.9739904175222451, "crossing": "?"}, {"age": 1.9739904175222451, "crossing": "?"}, {"age": 1.9739904175222451, "crossing": "?"}, {"age": 1.9739904175222451, "crossing": "?"}, {"age": 1.9739904175222451, "crossing": "?"}, {"age": 1.9739904175222451, "crossing": "?"}, {"age": 1.9739904175222451, "crossing": "?"}, {"age": 1.9739904175222451, "crossing": "?"}, {"age": 1.9739904175222451, "crossing": "?"}, {"age": 1.2566735112936345, "crossing": "?"}, {"age": 1.9739904175222451, "crossing": "?"}, {"age": 1.9739904175222451, "crossing": "?"}, {"age": 1.9739904175222451, "crossing": "?"}, {"age": 1.9739904175222451, "crossing": "?"}, {"age": 0.33127994524298426, "crossing": "?"}, {"age": 0.33127994524298426, "crossing": "?"}, {"age": 1.9739904175222451, "crossing": "?"}, {"age": 1.9739904175222451, "crossing": "?"}, {"age": 1.9739904175222451, "crossing": "?"}, {"age": 1.9739904175222451, "crossing": "?"}, {"age": 1.9739904175222451, "crossing": "?"}, {"age": 1.9739904175222451, "crossing": "?"}, {"age": 1.9739904175222451, "crossing": "?"}, {"age": 1.9739904175222451, "crossing": "?"}, {"age": 1.9739904175222451, "crossing": "?"}, {"age": 1.9739904175222451, "crossing": "?"}, {"age": 1.9739904175222451, "crossing": "?"}, {"age": 1.9739904175222451, "crossing": "?"}, {"age": 1.9739904175222451, "crossing": "?"}, {"age": 1.9739904175222451, "crossing": "?"}, {"age": 1.9739904175222451, "crossing": "?"}, {"age": 1.9739904175222451, "crossing": "?"}, {"age": 1.9739904175222451, "crossing": "?"}, {"age": 1.9739904175222451, "crossing": "?"}, {"age": 1.9739904175222451, "crossing": "?"}, {"age": 1.9739904175222451, "crossing": "?"}, {"age": 1.9739904175222451, "crossing": "?"}, {"age": 1.9739904175222451, "crossing": "?"}, {"age": 1.9739904175222451, "crossing": "?"}, {"age": 1.9739904175222451, "crossing": "?"}, {"age": 1.9739904175222451, "crossing": "?"}, {"age": 1.9739904175222451, "crossing": "?"}, {"age": 1.9739904175222451, "crossing": "?"}, {"age": 1.9739904175222451, "crossing": "?"}, {"age": 1.9739904175222451, "crossing": "?"}, {"age": 1.9739904175222451, "crossing": "?"}, {"age": 1.9739904175222451, "crossing": "?"}, {"age": 1.9739904175222451, "crossing": "?"}, {"age": 1.9739904175222451, "crossing": "?"}, {"age": 1.9739904175222451, "crossing": "?"}, {"age": 1.9739904175222451, "crossing": "?"}, {"age": 1.9739904175222451, "crossing": "?"}, {"age": 1.9739904175222451, "crossing": "?"}, {"age": 1.9739904175222451, "crossing": "?"}, {"age": 1.9739904175222451, "crossing": "?"}, {"age": 1.9739904175222451, "crossing": "?"}, {"age": 1.9739904175222451, "crossing": "?"}, {"age": 1.9739904175222451, "crossing": "?"}, {"age": 1.9739904175222451, "crossing": "?"}, {"age": 1.9739904175222451, "crossing": "?"}, {"age": 1.9739904175222451, "crossing": "?"}, {"age": 1.9739904175222451, "crossing": "?"}, {"age": 1.9739904175222451, "crossing": "?"}, {"age": 1.9739904175222451, "crossing": "?"}, {"age": 0.29842573579739906, "crossing": "?"}, {"age": 1.9739904175222451, "crossing": "?"}, {"age": 1.9739904175222451, "crossing": "?"}, {"age": 1.9739904175222451, "crossing": "?"}, {"age": 1.5550992470910336, "crossing": "?"}, {"age": 0.33127994524298426, "crossing": "?"}, {"age": 1.9739904175222451, "crossing": "?"}, {"age": 1.9739904175222451, "crossing": "?"}, {"age": 1.5879534565366187, "crossing": "?"}, {"age": 0.4134154688569473, "crossing": "?"}, {"age": 1.9739904175222451, "crossing": "?"}, {"age": 1.9739904175222451, "crossing": "?"}, {"age": 1.9739904175222451, "crossing": "?"}, {"age": 1.9739904175222451, "crossing": "?"}, {"age": 1.9739904175222451, "crossing": "?"}, {"age": 1.9739904175222451, "crossing": "?"}, {"age": 1.9739904175222451, "crossing": "?"}, {"age": 1.9739904175222451, "crossing": "?"}, {"age": 1.9739904175222451, "crossing": "?"}, {"age": 1.9739904175222451, "crossing": "?"}, {"age": 1.9739904175222451, "crossing": "?"}, {"age": 1.9739904175222451, "crossing": "?"}, {"age": 1.9739904175222451, "crossing": "?"}, {"age": 1.9739904175222451, "crossing": "?"}, {"age": 1.9739904175222451, "crossing": "?"}, {"age": 1.9739904175222451, "crossing": "?"}, {"age": 1.9739904175222451, "crossing": "?"}, {"age": 1.9739904175222451, "crossing": "?"}, {"age": 1.9739904175222451, "crossing": "?"}, {"age": 1.9739904175222451, "crossing": "?"}, {"age": 1.9739904175222451, "crossing": "?"}, {"age": 1.9739904175222451, "crossing": "?"}, {"age": 1.9739904175222451, "crossing": "?"}, {"age": 1.9739904175222451, "crossing": "?"}, {"age": 1.9739904175222451, "crossing": "?"}, {"age": 1.9739904175222451, "crossing": "?"}, {"age": 1.9739904175222451, "crossing": "?"}, {"age": 1.9739904175222451, "crossing": "?"}, {"age": 1.9739904175222451, "crossing": "?"}, {"age": 1.9739904175222451, "crossing": "?"}, {"age": 1.9739904175222451, "crossing": "?"}, {"age": 1.9739904175222451, "crossing": "?"}, {"age": 1.9739904175222451, "crossing": "?"}, {"age": 1.9739904175222451, "crossing": "?"}, {"age": 1.9739904175222451, "crossing": "?"}, {"age": 1.9739904175222451, "crossing": "?"}, {"age": 1.9739904175222451, "crossing": "?"}, {"age": 1.9739904175222451, "crossing": "?"}, {"age": 1.9739904175222451, "crossing": "?"}, {"age": 1.9739904175222451, "crossing": "?"}, {"age": 1.9739904175222451, "crossing": "?"}, {"age": 1.9739904175222451, "crossing": "?"}, {"age": 1.9739904175222451, "crossing": "?"}, {"age": 1.9739904175222451, "crossing": "?"}, {"age": 1.9739904175222451, "crossing": "?"}, {"age": 1.9739904175222451, "crossing": "?"}, {"age": 1.9739904175222451, "crossing": "?"}, {"age": 1.9739904175222451, "crossing": "?"}, {"age": 1.9739904175222451, "crossing": "?"}, {"age": 1.9739904175222451, "crossing": "?"}, {"age": 1.9739904175222451, "crossing": "?"}, {"age": 1.9739904175222451, "crossing": "?"}, {"age": 1.9739904175222451, "crossing": "?"}, {"age": 1.9739904175222451, "crossing": "?"}, {"age": 1.9739904175222451, "crossing": "?"}, {"age": 1.9739904175222451, "crossing": "?"}, {"age": 1.9739904175222451, "crossing": "?"}, {"age": 1.9739904175222451, "crossing": "?"}, {"age": 1.9739904175222451, "crossing": "?"}, {"age": 1.9739904175222451, "crossing": "?"}, {"age": 1.9739904175222451, "crossing": "?"}, {"age": 1.9739904175222451, "crossing": "?"}, {"age": 1.9739904175222451, "crossing": "?"}, {"age": 1.9739904175222451, "crossing": "?"}, {"age": 1.9739904175222451, "crossing": "?"}, {"age": 1.9739904175222451, "crossing": "?"}, {"age": 1.9739904175222451, "crossing": "?"}, {"age": 1.9739904175222451, "crossing": "?"}, {"age": 1.9739904175222451, "crossing": "?"}, {"age": 1.9739904175222451, "crossing": "?"}, {"age": 1.9739904175222451, "crossing": "?"}, {"age": 1.9739904175222451, "crossing": "?"}, {"age": 1.9739904175222451, "crossing": "?"}, {"age": 1.9739904175222451, "crossing": "?"}, {"age": 1.9739904175222451, "crossing": "?"}, {"age": 1.9739904175222451, "crossing": "?"}, {"age": 1.9739904175222451, "crossing": "?"}, {"age": 1.9739904175222451, "crossing": "?"}, {"age": 1.9739904175222451, "crossing": "?"}, {"age": 1.9739904175222451, "crossing": "?"}, {"age": 1.9739904175222451, "crossing": "?"}, {"age": 1.9739904175222451, "crossing": "?"}, {"age": 1.9739904175222451, "crossing": "?"}, {"age": 1.9739904175222451, "crossing": "?"}, {"age": 1.9739904175222451, "crossing": "?"}, {"age": 1.9739904175222451, "crossing": "?"}, {"age": 1.9739904175222451, "crossing": "?"}, {"age": 1.9739904175222451, "crossing": "?"}, {"age": 1.9739904175222451, "crossing": "?"}, {"age": 1.9739904175222451, "crossing": "?"}, {"age": 1.9739904175222451, "crossing": "?"}, {"age": 1.9739904175222451, "crossing": "?"}, {"age": 1.9739904175222451, "crossing": "?"}, {"age": 1.9739904175222451, "crossing": "?"}, {"age": 1.9739904175222451, "crossing": "?"}, {"age": 1.9739904175222451, "crossing": "?"}, {"age": 1.9739904175222451, "crossing": "?"}, {"age": 1.9739904175222451, "crossing": "?"}, {"age": 1.9739904175222451, "crossing": "?"}, {"age": 1.9739904175222451, "crossing": "?"}, {"age": 1.9739904175222451, "crossing": "?"}, {"age": 1.9739904175222451, "crossing": "?"}, {"age": 1.9739904175222451, "crossing": "?"}, {"age": 1.9739904175222451, "crossing": "?"}, {"age": 1.9739904175222451, "crossing": "?"}, {"age": 1.9739904175222451, "crossing": "?"}, {"age": 1.9739904175222451, "crossing": "?"}, {"age": 1.9739904175222451, "crossing": "?"}, {"age": 1.9739904175222451, "crossing": "?"}, {"age": 1.9739904175222451, "crossing": "?"}, {"age": 1.9739904175222451, "crossing": "?"}, {"age": 1.9739904175222451, "crossing": "?"}, {"age": 1.9739904175222451, "crossing": "?"}, {"age": 1.9739904175222451, "crossing": "?"}, {"age": 1.9739904175222451, "crossing": "?"}, {"age": 1.9739904175222451, "crossing": "?"}, {"age": 1.9739904175222451, "crossing": "?"}, {"age": 1.9739904175222451, "crossing": "?"}, {"age": 1.9739904175222451, "crossing": "?"}, {"age": 1.9739904175222451, "crossing": "?"}, {"age": 1.9739904175222451, "crossing": "?"}, {"age": 1.9739904175222451, "crossing": "?"}, {"age": 1.9739904175222451, "crossing": "?"}, {"age": 1.9739904175222451, "crossing": "?"}, {"age": 1.9739904175222451, "crossing": "?"}, {"age": 1.9739904175222451, "crossing": "?"}, {"age": 1.9739904175222451, "crossing": "?"}, {"age": 1.9739904175222451, "crossing": "?"}, {"age": 1.9739904175222451, "crossing": "?"}, {"age": 1.9739904175222451, "crossing": "?"}, {"age": 1.9739904175222451, "crossing": "?"}, {"age": 1.9739904175222451, "crossing": "?"}, {"age": 1.9739904175222451, "crossing": "?"}, {"age": 1.9739904175222451, "crossing": "?"}, {"age": 1.9739904175222451, "crossing": "?"}, {"age": 1.9739904175222451, "crossing": "?"}, {"age": 1.9739904175222451, "crossing": "?"}, {"age": 1.9739904175222451, "crossing": "?"}, {"age": 1.9739904175222451, "crossing": "?"}, {"age": 1.9739904175222451, "crossing": "?"}, {"age": 1.9739904175222451, "crossing": "?"}, {"age": 1.9739904175222451, "crossing": "?"}, {"age": 1.9739904175222451, "crossing": "?"}, {"age": 1.9739904175222451, "crossing": "?"}, {"age": 1.9739904175222451, "crossing": "?"}, {"age": 1.9739904175222451, "crossing": "?"}, {"age": 1.9739904175222451, "crossing": "?"}, {"age": 1.9739904175222451, "crossing": "?"}, {"age": 1.9739904175222451, "crossing": "?"}, {"age": 1.9739904175222451, "crossing": "?"}, {"age": 1.9739904175222451, "crossing": "?"}, {"age": 1.9739904175222451, "crossing": "?"}, {"age": 1.9739904175222451, "crossing": "?"}, {"age": 1.9739904175222451, "crossing": "?"}, {"age": 1.9739904175222451, "crossing": "?"}, {"age": 1.9739904175222451, "crossing": "?"}, {"age": 1.9739904175222451, "crossing": "?"}, {"age": 1.9739904175222451, "crossing": "?"}, {"age": 1.9739904175222451, "crossing": "?"}, {"age": 1.9739904175222451, "crossing": "?"}, {"age": 1.9739904175222451, "crossing": "?"}, {"age": 1.9739904175222451, "crossing": "?"}, {"age": 1.9739904175222451, "crossing": "?"}, {"age": 1.9739904175222451, "crossing": "?"}, {"age": 1.9739904175222451, "crossing": "?"}, {"age": 1.9739904175222451, "crossing": "?"}, {"age": 1.9739904175222451, "crossing": "?"}, {"age": 1.9739904175222451, "crossing": "?"}, {"age": 1.9739904175222451, "crossing": "?"}, {"age": 1.9739904175222451, "crossing": "?"}, {"age": 1.9739904175222451, "crossing": "?"}, {"age": 1.9739904175222451, "crossing": "?"}, {"age": 1.9739904175222451, "crossing": "?"}, {"age": 1.9739904175222451, "crossing": "?"}, {"age": 1.9739904175222451, "crossing": "?"}, {"age": 1.9739904175222451, "crossing": "?"}, {"age": 1.9739904175222451, "crossing": "?"}, {"age": 1.9739904175222451, "crossing": "?"}, {"age": 1.9739904175222451, "crossing": "?"}, {"age": 1.9739904175222451, "crossing": "?"}, {"age": 1.9739904175222451, "crossing": "?"}, {"age": 1.9739904175222451, "crossing": "?"}, {"age": 1.9739904175222451, "crossing": "?"}, {"age": 1.9739904175222451, "crossing": "?"}, {"age": 1.9739904175222451, "crossing": "?"}, {"age": 1.9739904175222451, "crossing": "?"}, {"age": 1.9739904175222451, "crossing": "?"}, {"age": 1.9739904175222451, "crossing": "?"}, {"age": 1.9739904175222451, "crossing": "?"}, {"age": 1.2566735112936345, "crossing": "?"}, {"age": 1.9739904175222451, "crossing": "?"}, {"age": 1.9739904175222451, "crossing": "?"}, {"age": 1.9739904175222451, "crossing": "?"}, {"age": 1.9739904175222451, "crossing": "?"}, {"age": 0.29842573579739906, "crossing": "?"}, {"age": 1.9739904175222451, "crossing": "?"}, {"age": 1.9739904175222451, "crossing": "?"}, {"age": 1.9739904175222451, "crossing": "?"}, {"age": 1.9739904175222451, "crossing": "?"}, {"age": 1.9739904175222451, "crossing": "?"}, {"age": 1.9739904175222451, "crossing": "?"}, {"age": 1.9739904175222451, "crossing": "?"}, {"age": 1.9739904175222451, "crossing": "?"}, {"age": 1.9739904175222451, "crossing": "?"}, {"age": 1.9739904175222451, "crossing": "?"}, {"age": 1.9739904175222451, "crossing": "?"}, {"age": 1.9739904175222451, "crossing": "?"}, {"age": 1.9739904175222451, "crossing": "?"}, {"age": 1.9739904175222451, "crossing": "?"}, {"age": 1.9739904175222451, "crossing": "?"}, {"age": 1.9739904175222451, "crossing": "?"}, {"age": 1.9739904175222451, "crossing": "?"}, {"age": 1.9739904175222451, "crossing": "?"}, {"age": 1.9739904175222451, "crossing": "?"}, {"age": 1.9739904175222451, "crossing": "?"}, {"age": 1.9739904175222451, "crossing": "?"}, {"age": 1.9739904175222451, "crossing": "?"}, {"age": 1.9739904175222451, "crossing": "?"}, {"age": 1.9739904175222451, "crossing": "?"}, {"age": 1.9739904175222451, "crossing": "?"}, {"age": 1.9739904175222451, "crossing": "?"}, {"age": 1.9739904175222451, "crossing": "?"}, {"age": 1.9739904175222451, "crossing": "?"}, {"age": 1.9739904175222451, "crossing": "?"}, {"age": 1.9739904175222451, "crossing": "?"}, {"age": 1.9739904175222451, "crossing": "?"}, {"age": 1.9739904175222451, "crossing": "?"}, {"age": 1.9739904175222451, "crossing": "?"}, {"age": 1.9739904175222451, "crossing": "?"}, {"age": 1.9739904175222451, "crossing": "?"}, {"age": 1.9739904175222451, "crossing": "?"}, {"age": 1.9739904175222451, "crossing": "?"}, {"age": 1.9739904175222451, "crossing": "?"}, {"age": 1.9739904175222451, "crossing": "?"}, {"age": 1.9739904175222451, "crossing": "?"}, {"age": 1.9739904175222451, "crossing": "?"}, {"age": 1.9739904175222451, "crossing": "?"}, {"age": 1.9739904175222451, "crossing": "?"}, {"age": 1.9739904175222451, "crossing": "?"}, {"age": 1.9739904175222451, "crossing": "?"}, {"age": 1.9739904175222451, "crossing": "?"}, {"age": 1.9739904175222451, "crossing": "?"}, {"age": 1.9739904175222451, "crossing": "?"}, {"age": 1.9739904175222451, "crossing": "?"}, {"age": 1.9739904175222451, "crossing": "?"}, {"age": 1.9739904175222451, "crossing": "?"}, {"age": 1.9739904175222451, "crossing": "?"}, {"age": 1.9739904175222451, "crossing": "?"}, {"age": 1.9739904175222451, "crossing": "?"}, {"age": 1.9739904175222451, "crossing": "?"}, {"age": 1.9739904175222451, "crossing": "?"}, {"age": 1.9739904175222451, "crossing": "?"}, {"age": 1.9739904175222451, "crossing": "?"}, {"age": 1.9739904175222451, "crossing": "?"}, {"age": 1.9739904175222451, "crossing": "?"}, {"age": 1.9739904175222451, "crossing": "?"}, {"age": 1.9739904175222451, "crossing": "?"}, {"age": 1.9739904175222451, "crossing": "?"}, {"age": 1.9739904175222451, "crossing": "?"}, {"age": 1.9739904175222451, "crossing": "?"}, {"age": 1.9739904175222451, "crossing": "?"}, {"age": 1.9739904175222451, "crossing": "?"}, {"age": 1.9739904175222451, "crossing": "?"}, {"age": 1.9739904175222451, "crossing": "?"}, {"age": 1.9739904175222451, "crossing": "?"}, {"age": 1.9739904175222451, "crossing": "?"}, {"age": 1.9739904175222451, "crossing": "?"}, {"age": 1.9739904175222451, "crossing": "?"}, {"age": 1.9739904175222451, "crossing": "?"}, {"age": 1.9739904175222451, "crossing": "?"}, {"age": 1.9739904175222451, "crossing": "?"}, {"age": 1.9739904175222451, "crossing": "?"}, {"age": 1.9739904175222451, "crossing": "?"}, {"age": 1.9739904175222451, "crossing": "?"}, {"age": 1.9739904175222451, "crossing": "?"}, {"age": 1.9739904175222451, "crossing": "?"}, {"age": 1.9739904175222451, "crossing": "?"}, {"age": 1.9739904175222451, "crossing": "?"}, {"age": 1.9739904175222451, "crossing": "?"}, {"age": 1.9739904175222451, "crossing": "?"}, {"age": 1.9739904175222451, "crossing": "?"}, {"age": 1.9739904175222451, "crossing": "?"}, {"age": 1.9739904175222451, "crossing": "?"}, {"age": 1.9739904175222451, "crossing": "?"}, {"age": 1.9739904175222451, "crossing": "?"}, {"age": 1.9739904175222451, "crossing": "?"}, {"age": 1.9739904175222451, "crossing": "?"}, {"age": 1.9739904175222451, "crossing": "?"}, {"age": 1.9739904175222451, "crossing": "?"}, {"age": 1.9739904175222451, "crossing": "?"}, {"age": 1.9739904175222451, "crossing": "?"}, {"age": 1.9739904175222451, "crossing": "?"}, {"age": 1.9739904175222451, "crossing": "?"}, {"age": 1.9739904175222451, "crossing": "?"}, {"age": 1.9739904175222451, "crossing": "?"}, {"age": 1.9739904175222451, "crossing": "?"}, {"age": 1.9739904175222451, "crossing": "?"}, {"age": 1.9739904175222451, "crossing": "?"}, {"age": 1.9739904175222451, "crossing": "?"}, {"age": 1.9739904175222451, "crossing": "?"}, {"age": 1.9739904175222451, "crossing": "?"}, {"age": 1.9739904175222451, "crossing": "?"}, {"age": 1.9739904175222451, "crossing": "?"}, {"age": 1.9739904175222451, "crossing": "?"}, {"age": 1.9739904175222451, "crossing": "?"}, {"age": 1.9739904175222451, "crossing": "?"}, {"age": 1.9739904175222451, "crossing": "?"}, {"age": 1.9739904175222451, "crossing": "?"}, {"age": 1.9739904175222451, "crossing": "?"}, {"age": 1.9739904175222451, "crossing": "?"}, {"age": 1.9739904175222451, "crossing": "?"}, {"age": 1.9739904175222451, "crossing": "?"}, {"age": 1.9739904175222451, "crossing": "?"}, {"age": 1.9739904175222451, "crossing": "?"}, {"age": 1.9739904175222451, "crossing": "?"}, {"age": 0.4134154688569473, "crossing": "?"}, {"age": 0.33127994524298426, "crossing": "?"}, {"age": 1.9739904175222451, "crossing": "?"}, {"age": 0.33127994524298426, "crossing": "?"}, {"age": 1.9739904175222451, "crossing": "?"}, {"age": 0.33127994524298426, "crossing": "?"}, {"age": 0.33127994524298426, "crossing": "?"}, {"age": 1.9739904175222451, "crossing": "?"}, {"age": 1.9739904175222451, "crossing": "?"}, {"age": 1.9739904175222451, "crossing": "?"}, {"age": 1.9739904175222451, "crossing": "?"}, {"age": 1.9739904175222451, "crossing": "?"}, {"age": 1.9739904175222451, "crossing": "?"}, {"age": 1.9739904175222451, "crossing": "?"}, {"age": 1.9739904175222451, "crossing": "?"}, {"age": 1.9739904175222451, "crossing": "?"}, {"age": 1.9739904175222451, "crossing": "?"}, {"age": 1.9739904175222451, "crossing": "?"}, {"age": 1.9739904175222451, "crossing": "?"}, {"age": 1.9739904175222451, "crossing": "?"}, {"age": 1.9739904175222451, "crossing": "?"}, {"age": 1.9739904175222451, "crossing": "?"}, {"age": 1.9739904175222451, "crossing": "?"}, {"age": 1.9739904175222451, "crossing": "?"}, {"age": 1.9739904175222451, "crossing": "?"}, {"age": 1.9739904175222451, "crossing": "?"}, {"age": 1.9739904175222451, "crossing": "?"}, {"age": 1.9739904175222451, "crossing": "?"}, {"age": 1.9739904175222451, "crossing": "?"}, {"age": 1.9739904175222451, "crossing": "?"}, {"age": 1.9739904175222451, "crossing": "?"}, {"age": 1.9739904175222451, "crossing": "?"}, {"age": 1.9739904175222451, "crossing": "?"}, {"age": 1.9739904175222451, "crossing": "?"}, {"age": 1.5879534565366187, "crossing": "?"}, {"age": 1.5879534565366187, "crossing": "?"}, {"age": 1.9739904175222451, "crossing": "?"}, {"age": 1.9739904175222451, "crossing": "?"}, {"age": 1.9739904175222451, "crossing": "uncontrolled"}, {"age": 1.7084188911704312, "crossing": "unmarked"}, {"age": 1.7084188911704312, "crossing": "unmarked"}, {"age": 1.620807665982204, "crossing": "unmarked"}, {"age": 0.12046543463381246, "crossing": "uncontrolled"}, {"age": 1.270362765229295, "crossing": "marked"}, {"age": 1.2238193018480492, "crossing": "?"}, {"age": 1.273100616016427, "crossing": "unmarked"}, {"age": 1.568788501026694, "crossing": "unmarked"}, {"age": 1.270362765229295, "crossing": "?"}, {"age": 1.1827515400410678, "crossing": "uncontrolled"}, {"age": 1.270362765229295, "crossing": "unmarked"}, {"age": 1.568788501026694, "crossing": "marked"}, {"age": 1.620807665982204, "crossing": "unmarked"}, {"age": 1.620807665982204, "crossing": "unmarked"}, {"age": 1.620807665982204, "crossing": "unmarked"}, {"age": 1.620807665982204, "crossing": "unmarked"}, {"age": 1.620807665982204, "crossing": "unmarked"}, {"age": 1.620807665982204, "crossing": "unmarked"}, {"age": 1.620807665982204, "crossing": "unmarked"}, {"age": 1.1800136892539357, "crossing": "unmarked"}, {"age": 0.7529089664613279, "crossing": "traffic_signals"}, {"age": 1.620807665982204, "crossing": "unmarked"}, {"age": 1.620807665982204, "crossing": "unmarked"}, {"age": 1.270362765229295, "crossing": "unmarked"}, {"age": 1.1800136892539357, "crossing": "unmarked"}, {"age": 1.5879534565366187, "crossing": "traffic_signals"}, {"age": 1.270362765229295, "crossing": "?"}, {"age": 1.568788501026694, "crossing": "unmarked"}, {"age": 1.568788501026694, "crossing": "unmarked"}, {"age": 1.568788501026694, "crossing": "marked"}, {"age": 1.568788501026694, "crossing": "unmarked"}, {"age": 0.7529089664613279, "crossing": "traffic_signals"}, {"age": 1.568788501026694, "crossing": "unmarked"}, {"age": 1.568788501026694, "crossing": "unmarked"}, {"age": 1.568788501026694, "crossing": "unmarked"}, {"age": 1.568788501026694, "crossing": "unmarked"}, {"age": 1.516769336071184, "crossing": "unmarked"}, {"age": 1.273100616016427, "crossing": "unmarked"}, {"age": 1.273100616016427, "crossing": "unmarked"}, {"age": 1.568788501026694, "crossing": "unmarked"}, {"age": 1.568788501026694, "crossing": "unmarked"}, {"age": 1.568788501026694, "crossing": "unmarked"}, {"age": 1.0595482546201231, "crossing": "unmarked"}, {"age": 1.273100616016427, "crossing": "uncontrolled"}, {"age": 1.273100616016427, "crossing": "unmarked"}, {"age": 1.568788501026694, "crossing": "unmarked"}, {"age": 0.03285420944558522, "crossing": "uncontrolled"}, {"age": 1.270362765229295, "crossing": "unmarked"}, {"age": 1.270362765229295, "crossing": "unmarked"}, {"age": 1.270362765229295, "crossing": "unmarked"}, {"age": 1.5359342915811087, "crossing": "unmarked"}, {"age": 1.270362765229295, "crossing": "unmarked"}, {"age": 1.270362765229295, "crossing": "unmarked"}, {"age": 1.5359342915811087, "crossing": "unmarked"}, {"age": 1.270362765229295, "crossing": "unmarked"}, {"age": 1.5359342915811087, "crossing": "unmarked"}, {"age": 1.5359342915811087, "crossing": "unmarked"}, {"age": 1.5359342915811087, "crossing": "unmarked"}, {"age": 1.5359342915811087, "crossing": "unmarked"}, {"age": 1.270362765229295, "crossing": "unmarked"}, {"age": 0.7474332648870636, "crossing": "uncontrolled"}, {"age": 0.7474332648870636, "crossing": "uncontrolled"}, {"age": 1.4017796030116358, "crossing": "unmarked"}, {"age": 1.4017796030116358, "crossing": "unmarked"}, {"age": 1.4017796030116358, "crossing": "unmarked"}, {"age": 1.4017796030116358, "crossing": "unmarked"}, {"age": 1.3388090349075976, "crossing": "uncontrolled"}, {"age": 1.3388090349075976, "crossing": "uncontrolled"}, {"age": 1.3388090349075976, "crossing": "uncontrolled"}, {"age": 1.3388090349075976, "crossing": "uncontrolled"}, {"age": 1.3388090349075976, "crossing": "traffic_signals"}, {"age": 1.3388090349075976, "crossing": "traffic_signals"}, {"age": 1.3388090349075976, "crossing": "traffic_signals"}, {"age": 1.3388090349075976, "crossing": "traffic_signals"}, {"age": 1.3388090349075976, "crossing": "traffic_signals"}, {"age": 1.3388090349075976, "crossing": "unmarked"}, {"age": 1.3388090349075976, "crossing": "unmarked"}, {"age": 1.3388090349075976, "crossing": "unmarked"}, {"age": 1.3388090349075976, "crossing": "uncontrolled"}, {"age": 1.3388090349075976, "crossing": "unmarked"}, {"age": 1.3388090349075976, "crossing": "unmarked"}, {"age": 1.3388090349075976, "crossing": "unmarked"}, {"age": 1.3388090349075976, "crossing": "unmarked"}, {"age": 1.3360711841204653, "crossing": "uncontrolled"}, {"age": 1.3360711841204653, "crossing": "traffic_signals"}, {"age": 1.3360711841204653, "crossing": "traffic_signals"}, {"age": 1.3360711841204653, "crossing": "traffic_signals"}, {"age": 1.3360711841204653, "crossing": "traffic_signals"}, {"age": 1.3360711841204653, "crossing": "traffic_signals"}, {"age": 1.3360711841204653, "crossing": "uncontrolled"}, {"age": 1.3305954825462012, "crossing": "traffic_signals"}, {"age": 1.3169062286105406, "crossing": "traffic_signals"}, {"age": 1.3141683778234086, "crossing": "uncontrolled"}, {"age": 1.3169062286105406, "crossing": "traffic_signals"}, {"age": 1.3169062286105406, "crossing": "uncontrolled"}, {"age": 1.3169062286105406, "crossing": "unmarked"}, {"age": 1.3169062286105406, "crossing": "unmarked"}, {"age": 1.3169062286105406, "crossing": "unmarked"}, {"age": 1.3169062286105406, "crossing": "unmarked"}, {"age": 1.3169062286105406, "crossing": "uncontrolled"}, {"age": 1.3169062286105406, "crossing": "uncontrolled"}, {"age": 0.7474332648870636, "crossing": "uncontrolled"}, {"age": 1.3169062286105406, "crossing": "traffic_signals"}, {"age": 1.3169062286105406, "crossing": "traffic_signals"}, {"age": 1.3169062286105406, "crossing": "traffic_signals"}, {"age": 1.3169062286105406, "crossing": "uncontrolled"}, {"age": 1.3169062286105406, "crossing": "traffic_signals"}, {"age": 1.3169062286105406, "crossing": "unmarked"}, {"age": 1.3169062286105406, "crossing": "uncontrolled"}, {"age": 1.3169062286105406, "crossing": "uncontrolled"}, {"age": 1.3169062286105406, "crossing": "traffic_signals"}, {"age": 1.3169062286105406, "crossing": "traffic_signals"}, {"age": 1.3059548254620124, "crossing": "uncontrolled"}, {"age": 1.3059548254620124, "crossing": "uncontrolled"}, {"age": 1.3059548254620124, "crossing": "uncontrolled"}, {"age": 1.3059548254620124, "crossing": "unmarked"}, {"age": 1.3059548254620124, "crossing": "uncontrolled"}, {"age": 1.3059548254620124, "crossing": "uncontrolled"}, {"age": 1.3059548254620124, "crossing": "uncontrolled"}, {"age": 1.3059548254620124, "crossing": "traffic_signals"}, {"age": 1.3059548254620124, "crossing": "traffic_signals"}, {"age": 1.3059548254620124, "crossing": "traffic_signals"}, {"age": 1.3059548254620124, "crossing": "uncontrolled"}, {"age": 1.3059548254620124, "crossing": "uncontrolled"}, {"age": 1.3059548254620124, "crossing": "uncontrolled"}, {"age": 1.3059548254620124, "crossing": "uncontrolled"}, {"age": 1.273100616016427, "crossing": "unmarked"}, {"age": 1.273100616016427, "crossing": "unmarked"}, {"age": 1.273100616016427, "crossing": "unmarked"}, {"age": 1.273100616016427, "crossing": "unmarked"}, {"age": 1.270362765229295, "crossing": "?"}, {"age": 1.273100616016427, "crossing": "unmarked"}, {"age": 1.273100616016427, "crossing": "unmarked"}, {"age": 1.273100616016427, "crossing": "unmarked"}, {"age": 1.273100616016427, "crossing": "unmarked"}, {"age": 1.273100616016427, "crossing": "?"}, {"age": 1.270362765229295, "crossing": "?"}, {"age": 1.270362765229295, "crossing": "?"}, {"age": 1.270362765229295, "crossing": "?"}, {"age": 1.270362765229295, "crossing": "?"}, {"age": 1.270362765229295, "crossing": "marked"}, {"age": 1.270362765229295, "crossing": "?"}, {"age": 1.270362765229295, "crossing": "?"}, {"age": 1.270362765229295, "crossing": "?"}, {"age": 1.270362765229295, "crossing": "?"}, {"age": 1.270362765229295, "crossing": "?"}, {"age": 1.270362765229295, "crossing": "?"}, {"age": 1.270362765229295, "crossing": "?"}, {"age": 1.270362765229295, "crossing": "?"}, {"age": 1.270362765229295, "crossing": "?"}, {"age": 1.270362765229295, "crossing": "?"}, {"age": 1.270362765229295, "crossing": "marked"}, {"age": 1.270362765229295, "crossing": "?"}, {"age": 1.270362765229295, "crossing": "?"}, {"age": 1.270362765229295, "crossing": "?"}, {"age": 1.270362765229295, "crossing": "?"}, {"age": 1.270362765229295, "crossing": "?"}, {"age": 1.270362765229295, "crossing": "?"}, {"age": 1.270362765229295, "crossing": "?"}, {"age": 1.270362765229295, "crossing": "?"}, {"age": 1.270362765229295, "crossing": "unmarked"}, {"age": 1.270362765229295, "crossing": "?"}, {"age": 1.270362765229295, "crossing": "unmarked"}, {"age": 1.270362765229295, "crossing": "marked"}, {"age": 0.7529089664613279, "crossing": "?"}, {"age": 1.270362765229295, "crossing": "?"}, {"age": 1.270362765229295, "crossing": "?"}, {"age": 1.270362765229295, "crossing": "?"}, {"age": 1.270362765229295, "crossing": "?"}, {"age": 1.270362765229295, "crossing": "?"}, {"age": 1.270362765229295, "crossing": "?"}, {"age": 1.270362765229295, "crossing": "?"}, {"age": 1.270362765229295, "crossing": "?"}, {"age": 1.270362765229295, "crossing": "?"}, {"age": 1.270362765229295, "crossing": "?"}, {"age": 1.270362765229295, "crossing": "?"}, {"age": 1.270362765229295, "crossing": "?"}, {"age": 0.7474332648870636, "crossing": "?"}, {"age": 1.270362765229295, "crossing": "?"}, {"age": 1.270362765229295, "crossing": "?"}, {"age": 1.270362765229295, "crossing": "?"}, {"age": 1.270362765229295, "crossing": "?"}, {"age": 1.270362765229295, "crossing": "?"}, {"age": 1.270362765229295, "crossing": "?"}, {"age": 1.270362765229295, "crossing": "?"}, {"age": 1.270362765229295, "crossing": "?"}, {"age": 1.270362765229295, "crossing": "?"}, {"age": 1.270362765229295, "crossing": "?"}, {"age": 1.270362765229295, "crossing": "?"}, {"age": 1.270362765229295, "crossing": "?"}, {"age": 1.270362765229295, "crossing": "?"}, {"age": 1.2238193018480492, "crossing": "?"}, {"age": 0.7529089664613279, "crossing": "?"}, {"age": 0.7529089664613279, "crossing": "?"}, {"age": 0.7529089664613279, "crossing": "traffic_signals"}, {"age": 1.1827515400410678, "crossing": "unmarked"}, {"age": 1.1827515400410678, "crossing": "unmarked"}, {"age": 1.1827515400410678, "crossing": "unmarked"}, {"age": 0.8788501026694046, "crossing": "unmarked"}, {"age": 1.1827515400410678, "crossing": "traffic_signals"}, {"age": 1.1827515400410678, "crossing": "traffic_signals"}, {"age": 1.1827515400410678, "crossing": "traffic_signals"}, {"age": 1.1827515400410678, "crossing": "traffic_signals"}, {"age": 1.1827515400410678, "crossing": "traffic_signals"}, {"age": 1.1827515400410678, "crossing": "unmarked"}, {"age": 1.1800136892539357, "crossing": "uncontrolled"}, {"age": 0.06023271731690623, "crossing": "uncontrolled"}, {"age": 1.1800136892539357, "crossing": "traffic_signals"}, {"age": 1.1800136892539357, "crossing": "unmarked"}, {"age": 1.1800136892539357, "crossing": "unmarked"}, {"age": 1.1800136892539357, "crossing": "unmarked"}, {"age": 1.1800136892539357, "crossing": "unmarked"}, {"age": 1.1800136892539357, "crossing": "traffic_signals"}, {"age": 1.1800136892539357, "crossing": "unmarked"}, {"age": 0.06023271731690623, "crossing": "uncontrolled"}, {"age": 0.06023271731690623, "crossing": "uncontrolled"}, {"age": 1.1800136892539357, "crossing": "unmarked"}, {"age": 1.1800136892539357, "crossing": "unmarked"}, {"age": 1.1800136892539357, "crossing": "traffic_signals"}, {"age": 1.1800136892539357, "crossing": "traffic_signals"}, {"age": 1.1800136892539357, "crossing": "unmarked"}, {"age": 1.1800136892539357, "crossing": "unmarked"}, {"age": 1.1800136892539357, "crossing": "unmarked"}, {"age": 1.1800136892539357, "crossing": "unmarked"}, {"age": 1.1800136892539357, "crossing": "unmarked"}, {"age": 1.0595482546201231, "crossing": "unmarked"}, {"age": 1.0595482546201231, "crossing": "unmarked"}, {"age": 1.0595482546201231, "crossing": "unmarked"}, {"age": 1.0595482546201231, "crossing": "unmarked"}, {"age": 1.0321697467488022, "crossing": "unmarked"}, {"age": 1.0595482546201231, "crossing": "unmarked"}, {"age": 1.0595482546201231, "crossing": "unmarked"}, {"age": 1.0595482546201231, "crossing": "uncontrolled"}, {"age": 1.0595482546201231, "crossing": "unmarked"}, {"age": 1.0595482546201231, "crossing": "unmarked"}, {"age": 1.0595482546201231, "crossing": "unmarked"}, {"age": 1.0595482546201231, "crossing": "unmarked"}, {"age": 1.0595482546201231, "crossing": "unmarked"}, {"age": 1.0239561943874058, "crossing": "uncontrolled"}, {"age": 1.0239561943874058, "crossing": "unmarked"}, {"age": 1.0239561943874058, "crossing": "uncontrolled"}, {"age": 1.0239561943874058, "crossing": "uncontrolled"}, {"age": 1.0239561943874058, "crossing": "uncontrolled"}, {"age": 1.0239561943874058, "crossing": "uncontrolled"}, {"age": 1.0239561943874058, "crossing": "uncontrolled"}, {"age": 1.0239561943874058, "crossing": "uncontrolled"}, {"age": 1.0239561943874058, "crossing": "unmarked"}, {"age": 1.0239561943874058, "crossing": "unmarked"}, {"age": 1.0239561943874058, "crossing": "unmarked"}, {"age": 1.0239561943874058, "crossing": "uncontrolled"}, {"age": 0.7474332648870636, "crossing": "traffic_signals"}, {"age": 0.7474332648870636, "crossing": "traffic_signals"}, {"age": 0.7474332648870636, "crossing": "traffic_signals"}, {"age": 0.7474332648870636, "crossing": "uncontrolled"}, {"age": 0.7474332648870636, "crossing": "uncontrolled"}, {"age": 0.7474332648870636, "crossing": "uncontrolled"}, {"age": 0.7474332648870636, "crossing": "uncontrolled"}, {"age": 0.6406570841889117, "crossing": "unmarked"}, {"age": 0.6406570841889117, "crossing": "uncontrolled"}, {"age": 0.6406570841889117, "crossing": "uncontrolled"}, {"age": 0.6406570841889117, "crossing": "uncontrolled"}, {"age": 0.6406570841889117, "crossing": "unmarked"}, {"age": 0.6406570841889117, "crossing": "unmarked"}, {"age": 0.6379192334017796, "crossing": "traffic_signals"}, {"age": 0.6379192334017796, "crossing": "traffic_signals"}, {"age": 0.6379192334017796, "crossing": "traffic_signals"}, {"age": 0.6324435318275154, "crossing": "traffic_signals"}, {"age": 0.6379192334017796, "crossing": "traffic_signals"}, {"age": 0.6379192334017796, "crossing": "traffic_signals"}, {"age": 0.31485284052019163, "crossing": "traffic_signals"}, {"age": 0.31485284052019163, "crossing": "traffic_signals"}, {"age": 0.6379192334017796, "crossing": "traffic_signals"}, {"age": 0.6379192334017796, "crossing": "traffic_signals"}, {"age": 0.6324435318275154, "crossing": "traffic_signals"}, {"age": 0.6324435318275154, "crossing": "traffic_signals"}, {"age": 0.6379192334017796, "crossing": "traffic_signals"}, {"age": 0.5913757700205339, "crossing": "?"}, {"age": 0.5913757700205339, "crossing": "?"}, {"age": 0.5913757700205339, "crossing": "?"}, {"age": 0.5913757700205339, "crossing": "traffic_signals"}, {"age": 0.5913757700205339, "crossing": "traffic_signals"}, {"age": 0.5913757700205339, "crossing": "traffic_signals"}, {"age": 0.5913757700205339, "crossing": "traffic_signals"}, {"age": 0.5913757700205339, "crossing": "unmarked"}, {"age": 0.5913757700205339, "crossing": "uncontrolled"}, {"age": 0.5913757700205339, "crossing": "traffic_signals"}, {"age": 0.5913757700205339, "crossing": "traffic_signals"}, {"age": 0.5913757700205339, "crossing": "uncontrolled"}, {"age": 0.5913757700205339, "crossing": "uncontrolled"}, {"age": 0.5913757700205339, "crossing": "unmarked"}, {"age": 0.5913757700205339, "crossing": "traffic_signals"}, {"age": 0.5913757700205339, "crossing": "traffic_signals"}, {"age": 0.5913757700205339, "crossing": "traffic_signals"}, {"age": 0.5913757700205339, "crossing": "uncontrolled"}, {"age": 0.5913757700205339, "crossing": "unmarked"}, {"age": 0.5913757700205339, "crossing": "unmarked"}, {"age": 0.5913757700205339, "crossing": "unmarked"}, {"age": 0.5913757700205339, "crossing": "unmarked"}, {"age": 0.5913757700205339, "crossing": "unmarked"}, {"age": 0.5776865160848734, "crossing": "uncontrolled"}, {"age": 0.5776865160848734, "crossing": "traffic_signals"}, {"age": 0.5776865160848734, "crossing": "traffic_signals"}, {"age": 0.5776865160848734, "crossing": "traffic_signals"}, {"age": 0.5776865160848734, "crossing": "uncontrolled"}, {"age": 0.2737850787132101, "crossing": "traffic_signals"}, {"age": 0.2737850787132101, "crossing": "traffic_signals"}, {"age": 0.2737850787132101, "crossing": "unmarked"}, {"age": 0.2737850787132101, "crossing": "unmarked"}, {"age": 0.2737850787132101, "crossing": "unmarked"}, {"age": 0.2737850787132101, "crossing": "unmarked"}, {"age": 0.13415468856947296, "crossing": "unmarked"}, {"age": 0.13415468856947296, "crossing": "unmarked"}, {"age": 0.13415468856947296, "crossing": "unmarked"}, {"age": 0.13415468856947296, "crossing": "unmarked"}, {"age": 0.13415468856947296, "crossing": "unmarked"}, {"age": 0.13415468856947296, "crossing": "unmarked"}, {"age": 0.13415468856947296, "crossing": "unmarked"}, {"age": 0.13141683778234087, "crossing": "uncontrolled"}, {"age": 0.13141683778234087, "crossing": "uncontrolled"}, {"age": 0.13141683778234087, "crossing": "unmarked"}, {"age": 0.13141683778234087, "crossing": "unmarked"}, {"age": 0.13141683778234087, "crossing": "unmarked"}, {"age": 0.13141683778234087, "crossing": "unmarked"}, {"age": 0.13141683778234087, "crossing": "unmarked"}, {"age": 0.13141683778234087, "crossing": "unmarked"}, {"age": 0.13141683778234087, "crossing": "unmarked"}, {"age": 0.12046543463381246, "crossing": "uncontrolled"}, {"age": 0.12046543463381246, "crossing": "unmarked"}, {"age": 0.12046543463381246, "crossing": "unmarked"}, {"age": 0.12046543463381246, "crossing": "unmarked"}, {"age": 0.12046543463381246, "crossing": "unmarked"}, {"age": 0.12046543463381246, "crossing": "unmarked"}, {"age": null, "crossing": "?"}, {"age": null, "crossing": "?"}, {"age": null, "crossing": "?"}, {"age": null, "crossing": "?"}, {"age": null, "crossing": "?"}, {"age": null, "crossing": "?"}, {"age": null, "crossing": "?"}, {"age": null, "crossing": "?"}, {"age": null, "crossing": "?"}, {"age": null, "crossing": "?"}, {"age": null, "crossing": "?"}, {"age": null, "crossing": "?"}, {"age": null, "crossing": "?"}, {"age": null, "crossing": "?"}]}}